{
  "users": [
    {
      "id": "1",
      "name": "Admin Gamer",
      "email": "admin@gmail.com",
      "password": "123"
    },
    {
      "id": "8551",
      "name": "nhannghia",
      "email": "nhannghialai@gmail.com",
      "password": "123456"
    },
    {
      "id": "f6d6",
      "name": "Na",
      "email": "22130175@st.hcmuaf.edu.vn",
      "password": "123567"
    }
  ],
  "orders": [
    {
      "id": "8ab5",
      "userId": "7e2c",
      "items": [
        {
          "id": 0,
          "name": "Cyberpunk 2077",
          "cover": "https://res.cloudinary.com/gianlucajahn/image/upload/c_scale,q_100,w_500/v1658188604/cyberpunk_n6jitl.jpg",
          "price": 59.99,
          "quantity": 1
        },
        {
          "id": 1,
          "name": "Battlefield V",
          "cover": "https://res.cloudinary.com/gianlucajahn/image/upload/c_scale,q_100,w_500/v1658188621/battlefield_n0gd5a.jpg",
          "price": 29.99,
          "quantity": 1
        }
      ],
      "totalAmount": 89.98,
      "date": "2025-12-08T17:09:57.601Z",
      "status": "Completed"
    },
    {
      "id": "9e23",
      "userId": "f6d6",
      "items": [
        {
          "id": "0",
          "name": "Cyberpunk 2077",
          "cover": "https://res.cloudinary.com/gianlucajahn/image/upload/c_scale,q_100,w_500/v1658188604/cyberpunk_n6jitl.jpg",
          "price": 59.99,
          "quantity": 1
        }
      ],
      "totalAmount": 59.99,
      "date": "2025-12-19T13:05:48.078Z",
      "status": "Completed"
    }
  ],
  "wishlist": [
    {
      "id": "3586",
      "userId": "1",
      "gameId": "0"
    },
    {
      "id": "fd3a",
      "userId": "1",
      "gameId": "1"
    }
  ],
  "reviews": [
    {
      "id": "95b5",
      "productId": "0",
      "userId": "8551",
      "user": "nhannghia",
      "rating": 5,
      "comment": "game rất hay mọi người nên chơi thử",
      "createdAt": "2025-12-20T08:42:05.242Z"
    },
    {
      "id": "bd19",
      "productId": "2",
      "userId": "8551",
      "user": "nhannghia",
      "rating": 1,
      "comment": "game quá tệ.không nên chơi",
      "createdAt": "2025-12-20T08:44:10.794Z"
    },
    {
      "id": "0a9f",
      "productId": "5",
      "userId": "8551",
      "user": "nhannghia",
      "rating": 5,
      "comment": "game rất hay\n",
      "createdAt": "2025-12-20T08:57:25.898Z"
    },
    {
      "id": "81cc",
      "productId": "1",
      "userId": "8551",
      "user": "nhannghia",
      "rating": 3,
      "comment": "game ko hay quá dở",
      "createdAt": "2025-12-20T12:47:48.273Z"
    },
    {
      "id": "0e86",
      "productId": "0",
      "userId": "1",
      "user": "Admin Gamer",
      "rating": 5,
      "comment": "game quá hay luôn\n",
      "createdAt": "2025-12-20T13:53:30.890Z"
    },
    {
      "id": "4a8d",
      "productId": "3",
      "userId": "8551",
      "user": "nhannghia",
      "rating": 1,
      "comment": "game nhạt quá\n",
      "createdAt": "2025-12-26T07:00:28.404Z"
    }
  ],
  "products": [
    {
      "name": "Cyberpunk 2077",
      "surname": "cyberpunk",
      "price": "346.500 ₫",
      "desc": "Cyberpunk 2077 là phần tiếp nối các sự kiện của Cyberpunk 2020, theo một hướng đi khác so với Cyberpunk V3.0. Trò chơi lấy bối cảnh tại siêu đô thị dystopia Night City, thuộc Tiểu bang Tự do Bắc California. Night City nằm ở phía nam San Francisco, quanh khu vực Morro Bay, CA. Trong Cyberpunk 2020, Night City được cho là có dân số hơn năm triệu người. Tuy nhiên, con số này được nghi ngờ là lớn hơn đáng kể vào năm 2077. Sau sự sụp đổ kinh tế vào đầu thế kỷ 21, Hoa Kỳ buộc phải phụ thuộc vào các tập đoàn lớn để tồn tại. Các tập đoàn này hoạt động trong nhiều lĩnh vực như vũ khí, robot, công nghệ sinh học, dược phẩm, truyền thông và công nghệ sinh học; nhiều công ty trong số này hoạt động trên cả luật pháp. Trò chơi theo chân câu chuyện của V — một tay súng thuê đang nổi lên tại Night City, siêu đô thị bạo lực và nguy hiểm nhất của tương lai bị thống trị bởi các tập đoàn. Hệ thống tạo nhân vật mạnh mẽ sẽ cho phép người chơi chọn giới tính, ngoại hình cũng như lý lịch lịch sử của V — tất cả có thể ảnh hưởng đến diễn biến của trò chơi. Thế giới lấy cảm hứng từ các tác phẩm của những tác giả như William Gibson (tác giả Neuromancer) và Philip K. Dick, với tiểu thuyết Do Androids Dream of Electric Sheep? cùng bản phim chuyển thể Blade Runner đã ảnh hưởng lớn đến người tạo ra, Mike Pondsmith, trong việc xây dựng trò chơi RPG bàn giấy gốc.",
      "link": "https://www.cyberpunk.net/",
      "release": "10 tháng 12 năm 2020",
      "platforms": "PC, PlayStation 5, Xbox Series X/S, Nintendo Switch 2, macOS",
      "genre": "Nhập vai",
      "developers": "CD Projekt RED",
      "publishers": "CD Projekt RED",
      "inCart": false,
      "selected": false,
      "isHovered": false,
      "isLiked": false,
      "rating": 78,
      "id": "0",
      "cover": "https://res.cloudinary.com/gianlucajahn/image/upload/c_scale,q_100,w_500/v1658188604/cyberpunk_n6jitl.jpg",
      "footage": [
        "https://res.cloudinary.com/gianlucajahn/image/upload/v1658188604/cyberpunk_n6jitl.jpg",
        "https://res.cloudinary.com/gianlucajahn/image/upload/c_scale,q_100,w_1920/v1658235373/cyberpunk_1_s00vwf.jpg",
        "https://res.cloudinary.com/gianlucajahn/image/upload/c_scale,q_100,w_1920/v1658235372/cyberpunk_2_mq46xm.jpg",
        "https://res.cloudinary.com/gianlucajahn/image/upload/c_scale,q_100,w_1920/v1658235378/cyberpunk_3_fajdmi.jpg"
      ]
    },
    {
      "name": "Battlefield V",
      "surname": "battlefield",
      "price": "199.000 ₫",
      "desc": "Series Battlefield quay về nguồn cội với hình ảnh chưa từng thấy về Chiến tranh Thế giới thứ 2. Tham gia vào các trận chiến multiplayer quy mô lớn cùng đồng đội trong các chế độ như Grand Operations hoành tráng và Combined Arms hợp tác, hoặc chứng kiến những câu chuyện nhân văn giữa bối cảnh chiến tranh toàn cầu qua chế độ chơi đơn War Stories. Chiến đấu ở những địa điểm hoành tráng, bất ngờ trên khắp thế giới và tận hưởng trải nghiệm Battlefield phong phú, sống động nhất từ trước đến nay.",
      "link": "https://www.origin.com/store/battlefield/battlefield-v",
      "release": "9 tháng 11 năm 2018",
      "platforms": "PlayStation 4, PC, Xbox Series X/S, Xbox One",
      "genre": "Bắn súng",
      "developers": "EA Digital Illusions CE",
      "publishers": "Electronic Arts",
      "inCart": false,
      "selected": false,
      "isHovered": false,
      "isLiked": false,
      "rating": 71,
      "id": "1",
      "cover": "https://res.cloudinary.com/gianlucajahn/image/upload/c_scale,q_100,w_500/v1658188621/battlefield_n0gd5a.jpg",
      "footage": [
        "https://res.cloudinary.com/gianlucajahn/image/upload/v1658188621/battlefield_n0gd5a.jpg",
        "https://res.cloudinary.com/gianlucajahn/image/upload/v1658235437/battlefield_1_jpudhq.jpg",
        "https://res.cloudinary.com/gianlucajahn/image/upload/v1658235437/battlefield_3_zy9ewv.jpg",
        "https://res.cloudinary.com/gianlucajahn/image/upload/v1658235438/battlefield_2_txs230.jpg"
      ]
    },
    {
      "name": "Life is Strange",
      "surname": "lis",
      "price": "99.000 ₫",
      "desc": "Life Is Strange là trò chơi episodic năm phần, cách mạng hóa thể loại game kể chuyện với lựa chọn và hậu quả bằng cách cho phép người chơi tua ngược thời gian và thay đổi quá khứ, hiện tại cũng như tương lai. Bạn vào vai Max, một học sinh năm cuối ngành nhiếp ảnh, người cứu người bạn cũ Chloe bằng cách phát hiện khả năng tua ngược thời gian. Cặp đôi nhanh chóng đối mặt với mặt tối của Arcadia Bay khi khám phá sự thật đáng sợ đằng sau vụ mất tích đột ngột của một học sinh khác. Đồng thời, Max bắt đầu có những linh cảm khi cố gắng hiểu ý nghĩa của sức mạnh của mình. Cô ấy phải nhanh chóng nhận ra rằng thay đổi quá khứ đôi khi có thể dẫn đến một tương lai thảm khốc.",
      "link": "https://lifeisstrange.square-enix-games.com/",
      "release": "30 tháng 1 năm 2015",
      "platforms": "PlayStation 4, PC, Xbox One, Xbox 360, PlayStation 3",
      "genre": "Phiêu lưu",
      "developers": "Dontnod Entertainment",
      "publishers": "Square Enix",
      "inCart": false,
      "selected": false,
      "isHovered": false,
      "isLiked": false,
      "rating": 83,
      "id": "2",
      "cover": "https://res.cloudinary.com/gianlucajahn/image/upload/c_scale,q_100,w_500/v1658188606/lis_ft0puo.jpg",
      "footage": [
        "https://res.cloudinary.com/gianlucajahn/image/upload/v1658188606/lis_ft0puo.jpg",
        "https://res.cloudinary.com/gianlucajahn/image/upload/v1658236055/lis_1_rkrxt5.jpg",
        "https://res.cloudinary.com/gianlucajahn/image/upload/v1658236272/lis_2_dcrdwz.jpg",
        "https://res.cloudinary.com/gianlucajahn/image/upload/v1658236055/lis_3_komskf.jpg"
      ]
    },
    {
      "name": "Mario Kart 8: Deluxe",
      "surname": "mariokart",
      "price": "1.200.000 ₫",
      "desc": "Hãy lên đường với phiên bản hoàn chỉnh nhất của Mario Kart 8 và chơi bất cứ lúc nào, bất cứ nơi đâu! Đua xe cùng bạn bè hoặc chiến đấu trong chế độ battle được cải tiến trên các đường đua mới và cũ. Chơi local multiplayer lên đến 4 người ở độ phân giải 1080p khi chơi ở chế độ TV. Tất cả các đường đua từ phiên bản Wii U, bao gồm cả DLC, đều trở lại. Thêm vào đó, Inklings xuất hiện như nhân vật khách mời mới, cùng với các nhân vật quen thuộc như King Boo, Dry Bones và Bowser Jr.!",
      "link": "https://mariokart8deluxe.nintendo.com/",
      "release": "28 tháng 4 năm 2017",
      "platforms": "Nintendo Switch",
      "genre": "Đua xe",
      "developers": "Nintendo EAD",
      "publishers": "Nintendo",
      "inCart": false,
      "selected": false,
      "isHovered": false,
      "isLiked": false,
      "rating": 84,
      "id": "3",
      "cover": "https://res.cloudinary.com/gianlucajahn/image/upload/c_scale,q_100,w_500/v1658232678/mariokart_0_mhgbeg.jpg",
      "footage": [
        "https://res.cloudinary.com/gianlucajahn/image/upload/v1658232678/mariokart_0_mhgbeg.jpg",
        "https://res.cloudinary.com/gianlucajahn/image/upload/c_scale,q_100,w_1920/v1658236315/mariokart_1_heekfq.jpg",
        "https://res.cloudinary.com/gianlucajahn/image/upload/c_scale,q_100,w_1920/v1658236316/mariokart_3_yzhdje.jpg",
        "https://res.cloudinary.com/gianlucajahn/image/upload/v1658236315/mariokart_2_peeyho.jpg"
      ]
    },
    {
      "name": "BioShock Infinite",
      "surname": "bioshockinfinite",
      "price": "120.000 ₫",
      "desc": "Đây là tựa game bắn súng góc nhìn thứ nhất theo cốt truyện thuộc series BioShock, theo chân Booker DeWitt khi anh bước vào thành phố bay độc lập Columbia (từng là của Mỹ) năm 1912 và cố gắng cứu một cô gái bị giam trong tháp bởi kẻ tự xưng là nhà tiên tri/độc tài của thành phố để xóa nợ tài chính. Trong suốt câu chuyện, các chủ đề về bạo lực, phân biệt chủng tộc và định mệnh được đề cập. Lưu ý: Game có nội dung dành cho người lớn.",
      "link": "https://2k.com/en-US/game/bioshock-infinite/",
      "release": "26 tháng 2 năm 2013",
      "platforms": "Xbox One, PlayStation 4, Linux, Xbox 360, PC, Nintendo Switch, PlayStation 3",
      "genre": "Phiêu lưu",
      "developers": "Irrational Games",
      "publishers": "2K Games",
      "inCart": false,
      "selected": false,
      "isHovered": false,
      "isLiked": false,
      "rating": 86,
      "id": "4",
      "cover": "https://res.cloudinary.com/gianlucajahn/image/upload/c_scale,q_100,w_500/v1658188602/bioshockinfinite_qyo3pi.jpg",
      "footage": [
        "https://res.cloudinary.com/gianlucajahn/image/upload/v1658188602/bioshockinfinite_qyo3pi.jpg",
        "https://res.cloudinary.com/gianlucajahn/image/upload/v1658236359/bioshockinfinite_1_vutin0.jpg",
        "https://res.cloudinary.com/gianlucajahn/image/upload/v1658236360/bioshockinfinite_2_bphusb.jpg",
        "https://res.cloudinary.com/gianlucajahn/image/upload/v1658236361/bioshockinfinite_3_v1ckvh.jpg"
      ]
    },
    {
      "name": "Anno 1800",
      "surname": "anno",
      "price": "250.000 ₫",
      "desc": "Anno 1800 diễn ra vào thế kỷ 19, thời kỳ bình minh của Cách mạng Công nghiệp. Giống như các tựa Anno khác, đây là game xây dựng thành phố và chiến lược. Bối cảnh là thương mại thuộc địa, với kiến trúc thời Victoria và nền kinh tế dựa trên lao động nhà máy. Lối chơi cốt lõi diễn ra ở Thế giới Cũ, nơi nhu cầu của công dân, công nhân và nghệ nhân là trung tâm quản lý sản xuất và chuỗi cung ứng. Một thành phố Thế giới Mới song song tồn tại, sản xuất hàng hóa mà lao động ở Thế giới Cũ muốn mua, do đó cần thiết lập tuyến thương mại. Không giống người tiền nhiệm Anno 1701, game có tính năng blueprint giúp người chơi lập kế hoạch thành phố.",
      "link": "https://anno-union.com/",
      "release": "16 tháng 4 năm 2019",
      "platforms": "PC (Microsoft Windows)",
      "genre": "Chiến thuật",
      "developers": "Blue Byte",
      "publishers": "Ubisoft",
      "inCart": false,
      "selected": false,
      "isHovered": false,
      "isLiked": false,
      "rating": 81,
      "id": "5",
      "cover": "https://res.cloudinary.com/gianlucajahn/image/upload/c_scale,q_100,w_500/v1658188622/anno_cbmzye.jpg",
      "footage": [
        "https://res.cloudinary.com/gianlucajahn/image/upload/v1658188622/anno_cbmzye.jpg",
        "https://res.cloudinary.com/gianlucajahn/image/upload/v1658236405/anno_1_bpil6t.jpg",
        "https://res.cloudinary.com/gianlucajahn/image/upload/c_scale,q_100,w_1920/v1658236405/anno_2_udh5ep.jpg",
        "https://res.cloudinary.com/gianlucajahn/image/upload/v1658236405/anno_3_hoqcp0.jpg"
      ]
    },
    {
      "name": "Red Dead Redemption 2",
      "surname": "rdr",
      "price": "450.000 ₫",
      "desc": "Nước Mỹ năm 1899. Kỷ nguyên miền Tây hoang dã đang kết thúc. Sau một vụ cướp thất bại ở thị trấn Blackwater, Arthur Morgan và băng Van der Linde buộc phải chạy trốn. Với lực lượng cơ quan liên bang và thợ săn tiền thưởng giỏi nhất quốc gia truy đuổi, băng đảng phải cướp bóc, trộm cắp và chiến đấu để sinh tồn trên vùng đất hoang dã của nước Mỹ. Khi những chia rẽ nội bộ ngày càng sâu sắc đe dọa xé tan băng đảng, Arthur phải lựa chọn giữa lý tưởng cá nhân và lòng trung thành với băng đảng đã nuôi dưỡng anh.",
      "link": "https://www.rockstargames.com/reddeadredemption2",
      "release": "26 tháng 10 năm 2018",
      "platforms": "Xbox One, PlayStation 4, PC, Google Stadia",
      "genre": "Nhập vai",
      "developers": "Rockstar Studios",
      "publishers": "Rockstar Games",
      "inCart": false,
      "selected": false,
      "isHovered": false,
      "isLiked": false,
      "rating": 92,
      "id": "6",
      "cover": "https://res.cloudinary.com/gianlucajahn/image/upload/c_scale,q_100,w_500/v1658188613/rdr_fhqs3d.jpg",
      "footage": [
        "https://res.cloudinary.com/gianlucajahn/image/upload/c_scale,w_1920/v1658188613/rdr_fhqs3d.jpg",
        "https://res.cloudinary.com/gianlucajahn/image/upload/v1658236494/rdr_3_euhfwh.jpg",
        "https://res.cloudinary.com/gianlucajahn/image/upload/c_scale,q_100,w_1920/v1658236495/rdr_2_aodums.jpg",
        "https://res.cloudinary.com/gianlucajahn/image/upload/v1658236494/rdr_1_v6xhov.jpg"
      ]
    },
    {
      "name": "Horizon Zero Dawn",
      "surname": "horizon",
      "price": "199.000 ₫",
      "desc": "Horizon Zero Dawn diễn ra vào thế kỷ 31, trong một thế giới hậu tận thế nơi những cỗ máy khổng lồ thống trị mặt đất. Nền văn minh nhân loại đã thoái hóa về các xã hội bộ lạc gồm thợ săn và hái lượm sống sót trong những khu rừng rộng lớn, dãy núi hùng vĩ và những tàn tích đầy không khí của tổ tiên họ – trong khi các cỗ máy ngày càng mạnh mẽ hơn. Người chơi điều khiển Aloy, một nữ thợ săn sử dụng tốc độ, sự khôn ngoan và linh hoạt để sống sót và bảo vệ bản thân cùng người khác trước sức mạnh, kích thước và lực lượng của các cỗ máy. Trò chơi kết hợp yếu tố khoa học viễn tưởng và thần thoại.",
      "link": "https://www.guerrilla-games.com/games",
      "release": "28 tháng 2 năm 2017",
      "platforms": "PlayStation 4, PC",
      "genre": "Phiêu lưu",
      "developers": "Guerrilla Games",
      "publishers": "Sony Interactive Entertainment",
      "inCart": false,
      "selected": false,
      "isHovered": false,
      "isLiked": false,
      "rating": 90,
      "id": "7",
      "cover": "https://res.cloudinary.com/gianlucajahn/image/upload/c_scale,q_100,w_500/v1658188606/horizon_jzlhsd.jpg",
      "footage": [
        "https://res.cloudinary.com/gianlucajahn/image/upload/v1658188606/horizon_jzlhsd.jpg",
        "https://res.cloudinary.com/gianlucajahn/image/upload/c_scale,q_100,w_1920/v1658236576/horizon_3_vwjcpi.jpg",
        "https://res.cloudinary.com/gianlucajahn/image/upload/v1658236574/horizon_2_ara05m.jpg",
        "https://res.cloudinary.com/gianlucajahn/image/upload/c_scale,q_100,w_1920/v1658236574/horizon_1_johwym.jpg"
      ]
    },
    {
      "name": "Grand Theft Auto: V",
      "surname": "gtav",
      "price": "399.000 ₫",
      "desc": "Grand Theft Auto V là một game thế giới mở rộng lớn lấy bối cảnh tại Los Santos, một siêu đô thị ngập nắng đang cố gắng tồn tại trong thời kỳ bất ổn kinh tế và truyền hình thực tế rẻ tiền. Trò chơi kết hợp kể chuyện và lối chơi theo cách mới khi người chơi liên tục nhảy vào và ra khỏi cuộc sống của ba nhân vật chính, chơi tất cả các bên trong câu chuyện đan xen của game.",
      "link": "https://www.rockstargames.com/gta-v",
      "release": "17 tháng 9 năm 2013",
      "platforms": "Xbox One, PlayStation 4, Xbox 360, PlayStation 5, PC, PlayStation 3, Xbox Series X/S",
      "genre": "Hành động",
      "developers": "Rockstar North",
      "publishers": "Rockstar Games",
      "inCart": false,
      "selected": false,
      "isHovered": false,
      "isLiked": false,
      "rating": 90,
      "id": "8",
      "cover": "https://res.cloudinary.com/gianlucajahn/image/upload/c_scale,q_100,w_500/v1658188604/gtav_x1ccio.jpg",
      "footage": [
        "https://res.cloudinary.com/gianlucajahn/image/upload/v1658188604/gtav_x1ccio.jpg",
        "https://res.cloudinary.com/gianlucajahn/image/upload/v1658236641/gtav_1_gkelkb.jpg",
        "https://res.cloudinary.com/gianlucajahn/image/upload/v1658236641/gtav_3_dswcgm.jpg",
        "https://res.cloudinary.com/gianlucajahn/image/upload/v1658236641/gtav_2_b1xno6.jpg"
      ]
    },
    {
      "name": "The Elder Scrolls: Skyrim",
      "surname": "skyrim",
      "price": "149.000 ₫",
      "desc": "Hai trăm năm đã trôi qua kể từ sự kiện trong The Elder Scrolls IV: Oblivion, và hiện tại là năm 4E 201. Vua Cao của Skyrim đã bị sát hại, và mối đe dọa nội chiến đang bao trùm vùng đất Skyrim; một bên muốn ly khai khỏi Đế chế Thứ Ba suy yếu, bên kia muốn tiếp tục là một phần của nó. Tệ hơn nữa, sự chia rẽ này là sự kiện cuối cùng trong lời tiên tri được ghi chép bởi Elder Scrolls sẽ dẫn đến sự trở lại của các con rồng dưới quyền Alduin, vị thần hủy diệt của người Nordic. Người chơi bắt đầu game trên xe ngựa hướng tới máy chém sau khi bị bắt cùng Stormcloaks trong một cuộc phục kích của Quân đoàn Đế quốc. Khi người chơi đặt đầu lên máy chém, con rồng Alduin tấn công. Trong hỗn loạn, Hadvar, vài Stormcloaks cùng thủ lĩnh và đồng tù Ulfric Stormcloak giúp người chơi trốn thoát. Người chơi có thể chọn sự trợ giúp của Ralof, Stormcloak đến cùng Ulfric, hoặc Hadvar, lính Đế quốc phụ trách đọc tên tù nhân bị hành quyết. Sau khi trợ giúp và nhận được sự ưu ái của Jarl Balgruuf the Greater, người chơi sau đó biết rằng mình là Dovahkiin, hay Dragonborn, người được giao nhiệm vụ đánh bại Alduin và các con rồng. Cuối cùng, người chơi gặp Delphine và Esbern, hai thành viên cuối cùng còn lại của Blades, và trở thành học trò của các Greybeards danh tiếng tại High Hrothgar.",
      "link": "https://elderscrolls.bethesda.net/de/",
      "release": "10 tháng 11 năm 2011",
      "platforms": "Xbox 360, PC (Microsoft Windows), PlayStation 3",
      "genre": "Nhập vai",
      "developers": "Bethesda Game Studios",
      "publishers": "Bethesda Softworks",
      "inCart": false,
      "selected": false,
      "isHovered": false,
      "isLiked": false,
      "rating": 88,
      "id": "9",
      "cover": "https://res.cloudinary.com/gianlucajahn/image/upload/c_scale,q_100,w_500/v1658584215/skyrim_js5pmg.jpg",
      "footage": [
        "https://res.cloudinary.com/gianlucajahn/image/upload/v1658584215/skyrim_js5pmg.jpg",
        "https://res.cloudinary.com/gianlucajahn/image/upload/v1658583241/skyrim_1_ludikr.jpg",
        "https://res.cloudinary.com/gianlucajahn/image/upload/c_scale,q_100,w_1920/v1658583241/skyrim_2_zgnhf5.jpg",
        "https://res.cloudinary.com/gianlucajahn/image/upload/c_scale,q_100,w_1920/v1658584731/maxresdefault_mciyjz.jpg"
      ]
    },
    {
      "name": "Warframe",
      "surname": "warframe",
      "price": "Miễn phí",
      "desc": "Warframe đặt người chơi vào vai thành viên của chủng tộc Tenno, vừa tỉnh giấc sau nhiều năm ngủ đông cryo vào một hệ mặt trời đang chiến tranh. Tái sinh trong một kỷ nguyên tham nhũng, Tenno bị Đế chế Grineer áp bức tìm cách tiêu diệt. Bộ giáp Warframe là chìa khóa để lật đổ Grineer bằng cách cung cấp cho người chơi các sức mạnh tấn công và phòng thủ độc đáo để khám phá, nâng cấp và làm chủ trong các cuộc đột kích radian có mục tiêu rõ ràng.",
      "link": "https://www.warframe.com/de/landing",
      "release": "25 tháng 3 năm 2013",
      "platforms": "Xbox One, PlayStation 4, PlayStation 5, PC, Nintendo Switch, Xbox Series X/S",
      "genre": "Hành động",
      "developers": "Digital Extremes",
      "publishers": "Digital Extremes",
      "inCart": false,
      "selected": false,
      "isHovered": false,
      "isLiked": false,
      "rating": 76,
      "id": "10",
      "cover": "https://res.cloudinary.com/gianlucajahn/image/upload/c_scale,q_100,w_500/v1658188601/warframe_kghu8g.jpg",
      "footage": [
        "https://res.cloudinary.com/gianlucajahn/image/upload/v1658188601/warframe_kghu8g.jpg",
        "https://res.cloudinary.com/gianlucajahn/image/upload/c_scale,q_100,w_1920/v1658236676/warframe_3_t2bwvx.jpg",
        "https://res.cloudinary.com/gianlucajahn/image/upload/c_scale,q_100,w_1920/v1658236676/warframe_2_ihvoqj.jpg",
        "https://res.cloudinary.com/gianlucajahn/image/upload/c_scale,q_100,w_1920/v1658236674/warframe_1_txaury.jpg"
      ]
    },
    {
      "name": "Minecraft",
      "surname": "minecraft",
      "price": "699.000 ₫",
      "desc": "Minecraft tập trung vào việc cho phép người chơi khám phá, tương tác và thay đổi một bản đồ được tạo ngẫu nhiên gồm các khối kích thước một mét khối. Ngoài các khối, môi trường còn có thực vật, quái vật và vật phẩm. Một số hoạt động trong game bao gồm khai thác quặng, chiến đấu với quái vật thù địch và chế tạo các khối mới cùng công cụ bằng cách thu thập các tài nguyên khác nhau trong game. Mô hình mở của game cho phép người chơi tạo cấu trúc, sáng tạo và tác phẩm nghệ thuật trên các server đa người hoặc bản đồ chơi đơn. Các tính năng khác bao gồm mạch redstone cho tính toán logic và hành động từ xa, xe đẩy mỏ và đường ray, cùng một thế giới ngầm bí ẩn gọi là Nether. Mục tiêu được chỉ định nhưng hoàn toàn tùy chọn của game là du hành đến một chiều không gian gọi là End và đánh bại ender dragon.",
      "link": "https://www.minecraft.net",
      "release": "15 tháng 8 năm 2011",
      "platforms": "Android, Linux, Mac, PC",
      "genre": "Sinh tồn",
      "developers": "Mojang",
      "publishers": "Mojang / Xbox Game Studios / Sony Interactive Entertainment",
      "inCart": false,
      "selected": false,
      "isHovered": false,
      "isLiked": false,
      "rating": 84,
      "id": "11",
      "cover": "https://res.cloudinary.com/gianlucajahn/image/upload/c_scale,q_100,w_500/v1658188606/minecraft_iuejtm.jpg",
      "footage": [
        "https://res.cloudinary.com/gianlucajahn/image/upload/v1658188606/minecraft_iuejtm.jpg",
        "https://res.cloudinary.com/gianlucajahn/image/upload/v1658236747/minecraft_2_pqo4tv.png",
        "https://res.cloudinary.com/gianlucajahn/image/upload/v1658236749/minecraft_1_vyp8bd.png",
        "https://res.cloudinary.com/gianlucajahn/image/upload/v1658236744/minecraft_3_cea2dc.png"
      ]
    },
    {
      "name": "Rise of the Tomb Raider",
      "surname": "riseofthetombraider",
      "price": "79.000 ₫",
      "desc": "Rise of the Tomb Raider là game hành động phiêu lưu góc nhìn thứ ba nơi người chơi điều khiển Lara Croft, đang trên hành trình khám phá thành phố huyền thoại Kitezh. Chiến đấu là cơ chế gameplay chính; Lara có nhiều loại vũ khí (bao gồm súng trường tấn công, súng ngắn và súng lục), một số có chế độ bắn thay thế. Người chơi cũng có thể sử dụng lén lút để tiến triển, dùng cung tên để hạ gục kẻ thù, tạo phân tâm để thu hút sự chú ý khỏi Lara, hoặc ẩn náu trong bụi rậm để tránh kẻ thù. Lara có thể sử dụng môi trường để chiến đấu, bắn thùng nổ, xé cấu trúc quấn dây bằng mũi tên dây, hoặc phục kích từ vị trí cao. Cô cũng có thể dùng rìu băng và dao chiến đấu để cận chiến với kẻ thù.",
      "link": "https://tombraider.square-enix-games.com/en-us",
      "release": "10 tháng 11 năm 2015",
      "platforms": "Xbox One, PlayStation 4, Linux, Xbox 360, Mac, PC, Google Stadia",
      "genre": "Phiêu lưu",
      "developers": "Crystal Dynamics",
      "publishers": "Microsoft Studios / Square Enix Europe",
      "inCart": false,
      "selected": false,
      "isHovered": false,
      "isLiked": false,
      "rating": 82,
      "id": "12",
      "cover": "https://res.cloudinary.com/gianlucajahn/image/upload/c_scale,q_100,w_500/v1658188610/riseofthetombraider_uq2q6t.jpg",
      "footage": [
        "https://res.cloudinary.com/gianlucajahn/image/upload/v1658188610/riseofthetombraider_uq2q6t.jpg",
        "https://res.cloudinary.com/gianlucajahn/image/upload/c_scale,q_100,w_1920/v1658236831/riseofthetombraider_2_vvhbqe.jpg",
        "https://res.cloudinary.com/gianlucajahn/image/upload/c_scale,q_100,w_1920/v1658236829/riseofthetombraider_1_bq8avn.jpg",
        "https://res.cloudinary.com/gianlucajahn/image/upload/c_scale,q_100,w_1920/v1658236830/riseofthetombraider_3_xm9ggz.jpg"
      ]
    },
    {
      "name": "Metro Exodus",
      "surname": "metro",
      "price": "129.000 ₫",
      "desc": "Metro Exodus là game bắn súng góc nhìn thứ nhất theo câu chuyện sử thi từ 4A Games kết hợp chiến đấu chết chóc và lén lút với khám phá và kinh dị sinh tồn trong một trong những thế giới game nhập vai nhất từng tạo ra. Khám phá vùng hoang dã Nga qua các cấp độ rộng lớn, phi tuyến tính và theo dõi một câu chuyện hấp dẫn kéo dài suốt một năm qua mùa xuân, hè, thu đến tận cùng mùa đông hạt nhân. Lấy cảm hứng từ tiểu thuyết của Dmitry Glukhovsky, Metro Exodus tiếp tục câu chuyện của Artyom trong cuộc phiêu lưu Metro vĩ đại nhất.",
      "link": "https://www.metrothegame.com/de/",
      "release": "15 tháng 2 năm 2019",
      "platforms": "Xbox One, PlayStation 4, PlayStation 5, PC, Xbox Series X/S, Google Stadia",
      "genre": "Bắn súng",
      "developers": "4A Games",
      "publishers": "Deep Silver",
      "inCart": false,
      "selected": false,
      "isHovered": false,
      "isLiked": false,
      "rating": 83,
      "id": "13",
      "cover": "https://res.cloudinary.com/gianlucajahn/image/upload/c_scale,q_100,w_500/v1658188608/metro_o45ytf.jpg",
      "footage": [
        "https://res.cloudinary.com/gianlucajahn/image/upload/v1658188608/metro_o45ytf.jpg",
        "https://res.cloudinary.com/gianlucajahn/image/upload/v1658236875/metro_1_mseeps.jpg",
        "https://res.cloudinary.com/gianlucajahn/image/upload/c_scale,q_100,w_1920/v1658236878/metro_2_wtk9ux.jpg",
        "https://res.cloudinary.com/gianlucajahn/image/upload/v1658236875/metro_3_y6ux12.jpg"
      ]
    },
    {
      "name": "Terraria",
      "surname": "terraria",
      "price": "119.000 ₫",
      "desc": "Đào, Chiến đấu, Khám phá, Xây dựng: Chính thế giới nằm trong tầm tay bạn khi chiến đấu để sinh tồn, tìm kiếm tài sản và vinh quang. Bạn sẽ đào sâu vào các hang động rộng lớn để tìm kho báu và nguyên liệu thô để chế tạo trang bị, máy móc và thẩm mỹ ngày càng tiến hóa? Có lẽ bạn sẽ chọn tìm kiếm những kẻ thù mạnh mẽ hơn để thử thách kỹ năng chiến đấu? Có thể bạn sẽ quyết định xây dựng thành phố riêng để chứa đựng vô số đồng minh bí ẩn mà bạn gặp trên hành trình? Trong Thế giới Terraria, lựa chọn thuộc về bạn!",
      "link": "https://terraria.org/",
      "release": "16 tháng 5 năm 2011",
      "platforms": "Nhiều nền tảng",
      "genre": "Sinh tồn",
      "developers": "Re-Logic",
      "publishers": "505 Games",
      "inCart": false,
      "selected": false,
      "isHovered": false,
      "isLiked": false,
      "rating": 81,
      "id": "14",
      "cover": "https://res.cloudinary.com/gianlucajahn/image/upload/c_scale,q_100,w_500/v1658188609/terraria_yb3iuc.jpg",
      "footage": [
        "https://res.cloudinary.com/gianlucajahn/image/upload/v1658188609/terraria_yb3iuc.jpg",
        "https://res.cloudinary.com/gianlucajahn/image/upload/v1658236904/terraria_1_sw79la.jpg",
        "https://res.cloudinary.com/gianlucajahn/image/upload/v1658236905/terraria_2_kqpdyq.jpg",
        "https://res.cloudinary.com/gianlucajahn/image/upload/v1658236905/terraria_3_wghczh.jpg"
      ]
    },
    {
      "name": "Rocket League",
      "surname": "rocketleague",
      "price": "69.000 ₫",
      "desc": "Rocket League là sự kết hợp mạnh mẽ giữa bóng đá phong cách arcade và hỗn loạn xe cộ với điều khiển dễ hiểu và cuộc thi dựa trên vật lý mượt mà. Rocket League bao gồm các trận đấu trực tuyến thông thường và cạnh tranh, chế độ Mùa offline đầy đủ tính năng, các “Mutators” đặc biệt cho phép thay đổi quy tắc hoàn toàn, các Chế độ Thêm lấy cảm hứng từ hockey và basketball, và hơn 500 nghìn tỷ kết hợp tùy chỉnh mỹ phẩm có thể.",
      "link": "https://www.rocketleague.com/",
      "release": "7 tháng 7 năm 2015",
      "platforms": "Xbox One, PlayStation 4, Linux, Mac, PlayStation 5, PC, Nintendo Switch, Xbox Series X/S",
      "genre": "Thể thao",
      "developers": "Psyonix",
      "publishers": "Psyonix",
      "inCart": false,
      "selected": false,
      "isHovered": false,
      "isLiked": false,
      "rating": 83,
      "id": "15",
      "cover": "https://res.cloudinary.com/gianlucajahn/image/upload/c_scale,q_100,w_500/v1658188608/rocketleague_on6yqd.jpg",
      "footage": [
        "https://res.cloudinary.com/gianlucajahn/image/upload/c_scale,w_1920/v1658188608/rocketleague_on6yqd.jpg",
        "https://res.cloudinary.com/gianlucajahn/image/upload/c_scale,q_100,w_1920/v1658236932/rocketleague_2_oogr9i.jpg",
        "https://res.cloudinary.com/gianlucajahn/image/upload/c_scale,q_100,w_1920/v1658236933/rocketleague_3_s6klzw.jpg",
        "https://res.cloudinary.com/gianlucajahn/image/upload/v1658236929/rocketleague_1_qcslm3.jpg"
      ]
    },
    {
      "name": "The Witcher 3: Wild Hunt",
      "surname": "thewitcher",
      "price": "199.000 ₫",
      "desc": "Game nhập vai và phần tiếp theo của The Witcher 2 (2011), The Witcher 3 theo chân witcher Geralt xứ Rivia khi anh tìm kiếm người yêu cũ và đứa trẻ được bảo hộ trong khi xen lẫn với các hoạt động chính trị của các Vương quốc Phương Bắc đang chiến tranh. Geralt phải chiến đấu với quái vật và đối phó với đủ loại người để giải quyết các vấn đề phức tạp và giải quyết tranh chấp gay gắt, từ cá nhân đến thay đổi thế giới.",
      "link": "https://www.thewitcher.com/en",
      "release": "19 tháng 5 năm 2015",
      "platforms": "Xbox One, PlayStation 4, PC, Nintendo Switch",
      "genre": "Nhập vai",
      "developers": "CD Projekt RED",
      "publishers": "CD Projekt",
      "inCart": false,
      "selected": false,
      "isHovered": false,
      "isLiked": false,
      "rating": 95,
      "id": "16",
      "cover": "https://res.cloudinary.com/gianlucajahn/image/upload/c_scale,q_100,w_500/v1658188610/thewitcher_tllr60.jpg",
      "footage": [
        "https://res.cloudinary.com/gianlucajahn/image/upload/v1658188610/thewitcher_tllr60.jpg",
        "https://res.cloudinary.com/gianlucajahn/image/upload/v1658236962/thewitcher_2_tipggu.jpg",
        "https://res.cloudinary.com/gianlucajahn/image/upload/v1658237770/witcher1_zgg86b.jpg",
        "https://res.cloudinary.com/gianlucajahn/image/upload/v1658236962/thewitcher_3_kyoymo.jpg"
      ]
    },
    {
      "name": "Hitman",
      "surname": "hitman",
      "price": "99.000 ₫",
      "desc": "Hãy trở thành Sát thủ bậc thầy trong một câu chuyện gián điệp ly kỳ đầy kịch tính. Với vai Agent 47, bạn thực hiện các hợp đồng ám sát nhắm vào những mục tiêu quyền lực, nổi bật tại các địa điểm kỳ lạ trên toàn thế giới. Lối chơi tập trung vào việc loại bỏ mục tiêu trong các cấp độ sandbox rộng lớn và phức tạp với sự tự do tiếp cận hoàn toàn. Đi đâu, tấn công khi nào và giết ai – tất cả đều do bạn quyết định.",
      "link": "https://hitman.com/global/",
      "release": "11 tháng 3 năm 2016",
      "platforms": "Xbox One, PlayStation 4, Linux, Mac, PC, Google Stadia",
      "genre": "Hành động",
      "developers": "IO Interactive",
      "publishers": "Square Enix Europe",
      "inCart": false,
      "selected": false,
      "isHovered": false,
      "isLiked": false,
      "rating": 81,
      "id": "17",
      "cover": "https://res.cloudinary.com/gianlucajahn/image/upload/c_scale,q_100,w_500/v1658188605/hitman_pqhnm6.jpg",
      "footage": [
        "https://res.cloudinary.com/gianlucajahn/image/upload/v1658188605/hitman_pqhnm6.jpg",
        "https://res.cloudinary.com/gianlucajahn/image/upload/v1658237949/hitman_yj2now.jpg",
        "https://res.cloudinary.com/gianlucajahn/image/upload/v1658237835/hitman_2_s3d61k.jpg",
        "https://res.cloudinary.com/gianlucajahn/image/upload/c_scale,q_100,w_1920/v1658237835/hitman_1_ny5whm.jpg"
      ]
    },
    {
      "name": "Fallout 4",
      "surname": "fallout",
      "price": "199.000 ₫",
      "desc": "Câu chuyện của Fallout 4 tập trung vào một người phối ngẫu, Người Sống Sót Duy Nhất từ Vault 111, khi họ tìm kiếm đứa con mất tích, Shaun. Fallout 4 lấy bối cảnh tại khu vực Boston và xung quanh vào năm 2287, 10 năm sau Fallout 3. Trên hành trình, Người Sống Sót Duy Nhất khám phá một thế giới sợ hãi một tổ chức bí ẩn gọi là Institute, bị ám ảnh bởi nỗi nghi ngờ về một chủng loài robot nhưng cũng mang tính sinh học giống người gọi là synth. Do cốt truyện tập trung vào synth, Người Sống Sót Duy Nhất cũng như người chơi phải đối mặt với các câu hỏi đạo đức như con người nên thử nghiệm khoa học đến mức nào, đạo đức của việc tạo ra những cỗ máy sống có tri giác biểu lộ cảm xúc và đau khổ, và ý nghĩa của việc làm người.",
      "link": "https://fallout.bethesda.net/en/games/fallout-4",
      "release": "10 tháng 11 năm 2015",
      "platforms": "Xbox One, PlayStation 4, PC",
      "genre": "Nhập vai",
      "developers": "Bethesda Game Studios",
      "publishers": "Bethesda Softworks",
      "inCart": false,
      "selected": false,
      "isHovered": false,
      "isLiked": false,
      "rating": 80,
      "id": "18",
      "cover": "https://res.cloudinary.com/gianlucajahn/image/upload/c_scale,q_100,w_500/v1658188603/fallout_kuxjw3.jpg",
      "footage": [
        "https://res.cloudinary.com/gianlucajahn/image/upload/v1658188603/fallout_kuxjw3.jpg",
        "https://res.cloudinary.com/gianlucajahn/image/upload/v1658238100/fallout_1_b4smuk.jpg",
        "https://res.cloudinary.com/gianlucajahn/image/upload/v1658238100/fallout_2_rlg0ng.jpg",
        "https://res.cloudinary.com/gianlucajahn/image/upload/v1658238100/fallout_3_tc6vd8.jpg"
      ]
    },
    {
      "name": "GTA: San Andreas",
      "surname": "gtasanandreas",
      "price": "149.000 ₫",
      "desc": "Sau vụ sát hại mẹ mình, Carl Johnson trở về thành phố bán hư cấu Los Santos (dựa trên Los Angeles). Là một cựu thành viên băng đảng, Carl phải giành lại đường phố cho gia đình và bạn bè bằng cách kiếm được sự tôn trọng và một lần nữa kiểm soát khu vực. Tuy nhiên, một câu chuyện đầy tội ác, dối trá và tham nhũng sẽ dẫn anh ta lang thang khắp tiểu bang San Andreas (dựa trên California và Nevada) để xây dựng lại cuộc đời.",
      "link": "https://www.rockstargames.com/games/sanandreas",
      "release": "26 tháng 10 năm 2004",
      "platforms": "Android, PlayStation 4, PlayStation 2, Xbox 360, Xbox, PC, PlayStation 3",
      "genre": "Hành động",
      "developers": "Rockstar North",
      "publishers": "Rockstar Games",
      "inCart": false,
      "selected": false,
      "isHovered": false,
      "isLiked": false,
      "rating": 90,
      "id": "19",
      "cover": "https://res.cloudinary.com/gianlucajahn/image/upload/c_scale,q_100,w_500/v1658188606/gtasanandreas_xkkyyp.jpg",
      "footage": [
        "https://res.cloudinary.com/gianlucajahn/image/upload/c_scale,w_1920/v1658188606/gtasanandreas_xkkyyp.jpg",
        "https://res.cloudinary.com/gianlucajahn/image/upload/v1658238143/gtasanandreas_1_zah5ph.jpg",
        "https://res.cloudinary.com/gianlucajahn/image/upload/v1658238142/gtasanandreas_2_vhvzyf.jpg",
        "https://res.cloudinary.com/gianlucajahn/image/upload/v1658238143/gtasanandreas_3_pb1aih.jpg"
      ]
    },
    {
      "name": "Golf with your Friends",
      "surname": "golfwithyourfriends",
      "price": "39.000 ₫",
      "desc": "Golf With Your Friends là một trò chơi mini golf đa người vui nhộn, thử thách dành cho tối đa 12 người chơi. Điều khiển đơn giản và game được thiết kế để người dùng có thể tạo hoặc tham gia trận đấu chỉ trong vài giây. Trận đấu sẽ được host trên server của chúng tôi, nơi người dùng có thể thêm mật khẩu nếu cần hoặc để mở cho công chúng. Người chơi trên PC có thể truy cập trình chỉnh sửa cấp độ để tạo bản đồ riêng hoặc thử hàng nghìn bản đồ do cộng đồng tạo.",
      "link": "http://www.blacklightinteractive.com/",
      "release": "29 tháng 1 năm 2016",
      "platforms": "Xbox One, PlayStation 4, Linux, PC, Nintendo Switch, Google Stadia",
      "genre": "Thể thao",
      "developers": "Blacklight Interactive",
      "publishers": "Team17 Digital / Blacklight Interactive",
      "inCart": false,
      "selected": false,
      "isHovered": false,
      "isLiked": false,
      "rating": 70,
      "id": "20",
      "cover": "https://res.cloudinary.com/gianlucajahn/image/upload/c_scale,q_100,w_500/v1658188609/golfwithyourfriends_rxrsbv.jpg",
      "footage": [
        "https://res.cloudinary.com/gianlucajahn/image/upload/v1658188609/golfwithyourfriends_rxrsbv.jpg",
        "https://res.cloudinary.com/gianlucajahn/image/upload/v1658238166/golfwithyourfriends_1_hoq6ii.jpg",
        "https://res.cloudinary.com/gianlucajahn/image/upload/v1658238166/golfwithyourfriends_2_zecdjb.jpg",
        "https://res.cloudinary.com/gianlucajahn/image/upload/v1658238166/golfwithyourfriends_3_euuouh.jpg"
      ]
    },
    {
      "name": "Heavy Rain",
      "surname": "heavyrain",
      "price": "49.000 ₫",
      "desc": "Heavy Rain là một bộ phim kinh dị tâm lý điện ảnh từ nhà phát triển game Quantic Dream dành riêng cho PlayStation 3. Xử lý nhiều chủ đề dành cho người lớn, game xoay quanh một cốt truyện tinh tế và các mạch truyện mạnh mẽ khám phá một đề xuất đạo đức phức tạp. Bạn đảm nhận vai nhiều nhân vật với nền tảng, động cơ và kỹ năng rất khác nhau trong một thế giới nơi mỗi quyết định của người chơi ảnh hưởng đến những gì sẽ xảy ra tiếp theo.",
      "link": "https://www.www.quanticdream.com/en/#!/en/category/heavy-rain",
      "release": "18 tháng 2 năm 2010",
      "platforms": "PlayStation 4, PC, PlayStation 3",
      "genre": "Phiêu lưu",
      "developers": "Quantic Dream",
      "publishers": "Sony Computer Entertainment / Quantic Dream",
      "inCart": false,
      "selected": false,
      "isHovered": false,
      "isLiked": false,
      "rating": 82,
      "id": "21",
      "cover": "https://res.cloudinary.com/gianlucajahn/image/upload/c_scale,q_100,w_500/v1658188605/heavyrain_bljnwv.jpg",
      "footage": [
        "https://res.cloudinary.com/gianlucajahn/image/upload/v1658188605/heavyrain_bljnwv.jpg",
        "https://res.cloudinary.com/gianlucajahn/image/upload/v1658238195/heavyrain_1_vvpszy.jpg",
        "https://res.cloudinary.com/gianlucajahn/image/upload/v1658238195/heavyrain_2_f8y4rn.jpg",
        "https://res.cloudinary.com/gianlucajahn/image/upload/v1658238196/heavyrain_3_fmkc8p.jpg"
      ]
    },
    {
      "name": "Dota 2",
      "surname": "dota",
      "price": "239.000 ₫",
      "desc": "Dota 2 là game cạnh tranh đội nhóm kiểu RTS-MOBA với yếu tố RPG. Hai đội đối thủ (Radiant và Dire) mỗi đội gồm năm người chơi. Mục tiêu chính trong Dota 2 là phá hủy Ancient của đối phương bên trong pháo đài. Các pháo đài này được bảo vệ bởi nhiều tháp dọc theo ba đường. Thay vì xây dựng quân lính như các game RTS cổ điển, mỗi người chơi điều khiển một Hero duy nhất, một đơn vị mạnh mẽ chiến lược với khả năng độc đáo và đặc trưng có thể cải thiện trong suốt trận đấu. Kinh nghiệm được kiếm khi creep và hero gần đó chết, và khi thu thập đủ kinh nghiệm, hero lên cấp, tăng chỉ số, và ở hầu hết các cấp hero nhận điểm kỹ năng để mở khóa hoặc nâng cấp một khả năng. Bên cạnh các khả năng cố định của hero, mỗi hero có 6 ô hành trang có thể chứa các Item mang lại lợi ích và khả năng đa dạng. Để mua các item này, Vàng được kiếm thụ động theo thời gian, bằng cách giết creep, giết hero địch và phá hủy công trình.",
      "link": "https://www.dota2.com/home",
      "release": "9 tháng 7 năm 2013",
      "platforms": "Linux, Mac, PC",
      "genre": "Chiến lược",
      "developers": "Valve",
      "publishers": "Valve",
      "inCart": false,
      "selected": false,
      "isHovered": false,
      "isLiked": false,
      "rating": 79,
      "id": "22",
      "cover": "https://res.cloudinary.com/gianlucajahn/image/upload/c_scale,q_100,w_500/v1658188603/dota_gdjxqx.jpg",
      "footage": [
        "https://res.cloudinary.com/gianlucajahn/image/upload/v1658188603/dota_gdjxqx.jpg",
        "https://res.cloudinary.com/gianlucajahn/image/upload/v1658238225/dota_1_lld4aw.jpg",
        "https://res.cloudinary.com/gianlucajahn/image/upload/v1658238227/dota_2_pguv1e.jpg",
        "https://res.cloudinary.com/gianlucajahn/image/upload/v1658238225/dota_3_ef1lec.jpg"
      ]
    },
    {
      "name": "Portal 2",
      "surname": "portal2",
      "price": "29.000 ₫",
      "desc": "Phần tiếp theo của Portal (2007) được đánh giá cao, Portal 2 đặt nhân vật chính của game gốc, Chell, và người bạn robot mới Wheatley đối mặt với nhiều câu đố do GLaDOS, một AI chỉ có mục đích thử nghiệm cơ chế Portal Gun và trả thù Chell vì sự kiện trong Portal, nghĩ ra. Do một số tương tác và tiết lộ, Chell một lần nữa cố gắng thoát khỏi Aperture Science Labs.",
      "link": "https://www.thinkwithportals.com/",
      "release": "19 tháng 4 năm 2011",
      "platforms": "Linux, Xbox 360, Mac, PC, PlayStation 3",
      "genre": "Giải đố",
      "developers": "Valve",
      "publishers": "Valve",
      "inCart": false,
      "selected": false,
      "isHovered": false,
      "isLiked": false,
      "rating": 92,
      "id": "23",
      "cover": "https://res.cloudinary.com/gianlucajahn/image/upload/c_scale,q_100,w_500/v1658188606/portal2_eugfiq.jpg",
      "footage": [
        "https://res.cloudinary.com/gianlucajahn/image/upload/v1658188606/portal2_eugfiq.jpg",
        "https://res.cloudinary.com/gianlucajahn/image/upload/v1658238290/portal2_1_tm6kyw.jpg",
        "https://res.cloudinary.com/gianlucajahn/image/upload/v1658238290/portal2_2_kmrlol.jpg",
        "https://res.cloudinary.com/gianlucajahn/image/upload/v1658238292/portal2_3_pjhzkj.jpg"
      ]
    },
    {
      "name": "Sid Meier's Civilization VI",
      "surname": "civilization",
      "price": "149.000 ₫",
      "desc": "Civilization là game chiến lược theo lượt nơi bạn cố gắng xây dựng một đế chế trường tồn theo thời gian. Trở thành Lãnh tụ Thế giới bằng cách thành lập và lãnh đạo một nền văn minh từ Thời kỳ Đồ đá đến Thời kỳ Thông tin. Phát động chiến tranh, ngoại giao, phát triển văn hóa, và đối đầu với các lãnh tụ vĩ đại nhất lịch sử khi bạn cố gắng xây dựng nền văn minh vĩ đại nhất mà thế giới từng biết.",
      "link": "https://www.civilization.com/",
      "release": "20 tháng 10 năm 2016",
      "platforms": "Xbox One, PlayStation 4, Linux, Mac, iOS, PC, Nintendo Switch",
      "genre": "Chiến lược",
      "developers": "Firaxis Games",
      "publishers": "2K Games / Aspyr Media",
      "inCart": false,
      "selected": false,
      "isHovered": false,
      "isLiked": false,
      "rating": 82,
      "id": "24",
      "cover": "https://res.cloudinary.com/gianlucajahn/image/upload/c_scale,q_100,w_500/v1658188603/civilization_jcuqap.jpg",
      "footage": [
        "https://res.cloudinary.com/gianlucajahn/image/upload/v1658188603/civilization_jcuqap.jpg",
        "https://res.cloudinary.com/gianlucajahn/image/upload/c_scale,q_100,w_1920/v1658238319/civilization_2_gpuqrk.jpg",
        "https://res.cloudinary.com/gianlucajahn/image/upload/c_scale,q_100,w_1920/v1658238319/civilization_1_cc21ew.jpg",
        "https://res.cloudinary.com/gianlucajahn/image/upload/v1658238318/civilization_3_qv8ben.jpg"
      ]
    },
    {
      "name": "God of War",
      "surname": "godofwar",
      "price": "499.000 ₫",
      "desc": "Nhiều năm đã trôi qua kể từ khi Kratos trả thù các vị thần Olympus. Sau khi sống sót sau cuộc gặp cuối cùng với cha mình Zeus, Kratos đã đến Midgard ở Na Uy cổ đại và giờ sống cùng con trai nhỏ Atreus trong thế giới của các vị thần Norse, một vùng đất hoang dã đầy quái vật và chiến binh hung dữ. Để dạy con trai mình, người mẹ (và vợ thứ hai của Kratos) vừa qua đời, cách sống sót trong thế giới như vậy, Kratos phải làm chủ cơn giận đã dẫn dắt anh nhiều năm và chấp nhận vai trò mới là một người cha và người cố vấn.",
      "link": "https://www.playstation.com/de-de/god-of-war/",
      "release": "20 tháng 4 năm 2018",
      "platforms": "PlayStation 4, PC",
      "genre": "Phiêu lưu",
      "developers": "Santa Monica Studio",
      "publishers": "Sony Interactive Entertainment",
      "inCart": false,
      "selected": false,
      "isHovered": false,
      "isLiked": false,
      "rating": 94,
      "id": "25",
      "cover": "https://res.cloudinary.com/gianlucajahn/image/upload/c_scale,q_100,w_500/v1658188602/godofwar_cbqzk1.jpg",
      "footage": [
        "https://res.cloudinary.com/gianlucajahn/image/upload/v1658188602/godofwar_cbqzk1.jpg",
        "https://res.cloudinary.com/gianlucajahn/image/upload/v1658238374/godofwar_1_c7k5as.jpg",
        "https://res.cloudinary.com/gianlucajahn/image/upload/v1658238373/godofwar_2_tiemyf.jpg",
        "https://res.cloudinary.com/gianlucajahn/image/upload/v1658238377/godofwar_3_qohtw3.jpg"
      ]
    },
    {
      "name": "FIFA 22",
      "surname": "fifa",
      "price": "599.000 ₫",
      "desc": "Được cung cấp bởi Football, FIFA 22 mang trò chơi gần hơn với thực tế với các tiến bộ gameplay cơ bản và một mùa sáng tạo mới trên mọi chế độ. Chơi với hơn 17.000 cầu thủ, hơn 700 đội tại hơn 90 sân vận động và hơn 30 giải đấu từ khắp nơi trên thế giới.",
      "link": "https://www.ea.com/de-de/games/fifa/fifa-22",
      "release": "30 tháng 9 năm 2021",
      "platforms": "Xbox One, PlayStation 4, PlayStation 5, PC, Xbox Series X/S, Google Stadia",
      "genre": "Thể thao",
      "developers": "EA Vancouver / EA Romania",
      "publishers": "EA Sports",
      "inCart": false,
      "selected": false,
      "isHovered": false,
      "isLiked": false,
      "rating": 80,
      "id": "26",
      "cover": "https://res.cloudinary.com/gianlucajahn/image/upload/c_scale,q_100,w_500/v1658188603/fifa_zb6ook.jpg",
      "footage": [
        "https://res.cloudinary.com/gianlucajahn/image/upload/v1658188603/fifa_zb6ook.jpg",
        "https://res.cloudinary.com/gianlucajahn/image/upload/v1658238407/fifa_1_tt7wm8.jpg",
        "https://res.cloudinary.com/gianlucajahn/image/upload/v1658582251/fifa3_faiswk.jpg",
        "https://res.cloudinary.com/gianlucajahn/image/upload/v1658238406/fifa_3_rwnx2k.jpg"
      ]
    },
    {
      "name": "Half-Life 2",
      "surname": "halflife",
      "price": "49.000 ₫",
      "desc": "Năm 1998, HALF-LIFE đã tạo cú sốc cho ngành công nghiệp game với sự kết hợp giữa hành động dồn dập và cốt truyện liên tục, nhập tâm. Bằng cách kế thừa sự hồi hộp, thử thách và cảm xúc nội tâm từ bản gốc, đồng thời thêm tính chân thực và phản hồi gây sửng sốt, Half-Life 2 mở ra một thế giới nơi sự hiện diện của người chơi ảnh hưởng đến mọi thứ xung quanh, từ môi trường vật lý đến hành vi và thậm chí cảm xúc của cả bạn bè lẫn kẻ thù.",
      "link": "https://www.half-life.com/en/halflife2",
      "release": "16 tháng 11 năm 2004",
      "platforms": "Android, Linux, Xbox 360, Mac, Xbox, PC, PlayStation 3",
      "genre": "Bắn súng",
      "developers": "Valve",
      "publishers": "Valve",
      "inCart": false,
      "selected": false,
      "isHovered": false,
      "isLiked": false,
      "rating": 91,
      "id": "27",
      "cover": "https://res.cloudinary.com/gianlucajahn/image/upload/c_scale,q_100,w_500/v1658188604/halflife_fiorjc.jpg",
      "footage": [
        "https://res.cloudinary.com/gianlucajahn/image/upload/v1658188604/halflife_fiorjc.jpg",
        "https://res.cloudinary.com/gianlucajahn/image/upload/v1658238448/halflife_1_nhsnrj.jpg",
        "https://res.cloudinary.com/gianlucajahn/image/upload/v1658238448/halflife_2_wpnvmz.jpg",
        "https://res.cloudinary.com/gianlucajahn/image/upload/v1658238450/halflife_3_xgil4x.jpg"
      ]
    },
    {
      "name": "The Walking Dead: S1",
      "surname": "twd",
      "price": "205.000 ₫",
      "desc": "The Walking Dead: Season One (còn gọi là The Walking Dead: The Game) là game phiêu lưu đồ họa tương tác theo tập do Telltale Games phát triển và phát hành. Dựa trên series truyện tranh The Walking Dead của Robert Kirkman, game gồm năm tập, phát hành từ tháng 4 đến tháng 11 năm 2012. Game có mặt trên Android, iOS, Kindle Fire HDX, Microsoft Windows, Mac OS X, PlayStation 3, PlayStation Vita, Xbox 360, PlayStation 4 và Xbox One. Đây là phần đầu tiên trong series game The Walking Dead của Telltale.",
      "link": "http://www.thewalkingdeadgame.com/",
      "release": "24 tháng 4 năm 2012",
      "platforms": "Android, Xbox One, PlayStation 4, Xbox 360, PC, Nintendo Switch, PlayStation 3",
      "genre": "Phiêu lưu",
      "developers": "Telltale Games",
      "publishers": "Telltale Games",
      "inCart": false,
      "selected": false,
      "isHovered": false,
      "isLiked": false,
      "rating": 86,
      "id": "28",
      "cover": "https://res.cloudinary.com/gianlucajahn/image/upload/c_scale,q_100,w_500/v1658188600/twd_dmycxx.jpg",
      "footage": [
        "https://res.cloudinary.com/gianlucajahn/image/upload/v1658188600/twd_dmycxx.jpg",
        "https://res.cloudinary.com/gianlucajahn/image/upload/v1658238474/twd_1_l4bv5v.jpg",
        "https://res.cloudinary.com/gianlucajahn/image/upload/v1658238474/twd_2_m9rg9r.jpg",
        "https://res.cloudinary.com/gianlucajahn/image/upload/v1658238474/twd_3_cclznv.jpg"
      ]
    },
    {
      "name": "Crusader Kings III",
      "surname": "crusaderkings",
      "price": "249.000 ₫",
      "desc": "Giống như các phần trước Crusader Kings và Crusader Kings II, Crusader Kings III là game chiến lược lớn và mô phỏng triều đại lấy bối cảnh Trung Cổ. Người chơi bắt đầu với một nhân vật vào năm 867 hoặc 1066. Bản đồ game chi tiết gấp bốn lần so với Crusader Kings II và lớn hơn một chút, bao gồm châu Âu, châu Phi đến tận xích đạo phía nam, và châu Á đến tận Tây Tạng phía đông. Khi nhân vật của người chơi chết hoặc bị phế truất, họ có thể tiếp tục chơi với người thừa kế. Tổng thể, người chơi phát triển một triều đại qua nhiều thế kỷ, game kết thúc vào năm 1453.",
      "link": "https://www.paradoxinteractive.com/games/crusader-kings-iii/about",
      "release": "1 tháng 9 năm 2020",
      "platforms": "Linux, Mac, PlayStation 5, PC, Xbox Series X/S",
      "genre": "Chiến lược",
      "developers": "Paradox Development Studios",
      "publishers": "Paradox Interactive",
      "inCart": false,
      "selected": false,
      "isHovered": false,
      "isLiked": false,
      "rating": 85,
      "id": "29",
      "cover": "https://res.cloudinary.com/gianlucajahn/image/upload/c_scale,q_100,w_500/v1658188601/crusaderkings_fpz1te.jpg",
      "footage": [
        "https://res.cloudinary.com/gianlucajahn/image/upload/v1658188601/crusaderkings_fpz1te.jpg",
        "https://res.cloudinary.com/gianlucajahn/image/upload/c_scale,q_100,w_1920/v1658238507/crusaderkings_1_m5wm5p.jpg",
        "https://res.cloudinary.com/gianlucajahn/image/upload/v1658238507/crusaderkings_2_pmrmcc.jpg",
        "https://res.cloudinary.com/gianlucajahn/image/upload/v1658238506/crusaderkings_3_hdzha4.jpg"
      ]
    },
    {
      "name": "Counter Strike: GO",
      "surname": "csgo",
      "price": "99.000 ₫",
      "desc": "Counter-Strike: Global Offensive (CS:GO) là game bắn súng góc nhìn thứ nhất thuộc series Counter-Strike. Game được công bố ngày 12 tháng 8 năm 2011, phát triển bởi Valve Corporation và đối tác Hidden Path Entertainment. Game phát hành ngày 21 tháng 8 năm 2012 cho PlayStation 3, Xbox 360, Microsoft Windows, macOS và sau đó là Linux dưới dạng tải về. (Lưu ý: Hiện đã được thay thế bởi Counter-Strike 2 miễn phí).",
      "link": "https://blog.counter-strike.net/",
      "release": "21 tháng 8 năm 2012",
      "platforms": "Linux, Xbox 360, Mac, PC, PlayStation 3",
      "genre": "Bắn súng",
      "developers": "Valve / Hidden Path Entertainment",
      "publishers": "Valve",
      "inCart": false,
      "selected": false,
      "isHovered": false,
      "isLiked": false,
      "rating": 82,
      "id": "30",
      "cover": "https://res.cloudinary.com/gianlucajahn/image/upload/c_scale,q_100,w_500/v1658188600/csgo_o9whdd.jpg",
      "footage": [
        "https://res.cloudinary.com/gianlucajahn/image/upload/v1658188600/csgo_o9whdd.jpg",
        "https://res.cloudinary.com/gianlucajahn/image/upload/v1658238547/csgo_1_gne318.jpg",
        "https://res.cloudinary.com/gianlucajahn/image/upload/v1658238546/csgo_2_j1tgfo.jpg",
        "https://res.cloudinary.com/gianlucajahn/image/upload/v1658238546/csgo_3_qgcwjw.jpg"
      ]
    },
    {
      "name": "Detroit: Become Human",
      "surname": "detroit",
      "price": "68.000 ₫",
      "desc": "Lấy bối cảnh Detroit năm 2038, thành phố đã hồi sinh nhờ phát minh và đưa android vào đời sống hàng ngày. Nhưng khi android bắt đầu hành xử như thể chúng đang sống, mọi thứ bắt đầu mất kiểm soát. Bạn sẽ hóa thân vào ba nhân vật chính có thể chơi (Kara, Connor và Markus), mỗi nhân vật có góc nhìn, động cơ và khả năng riêng biệt khi đối mặt với bản ngã thực sự và đặt câu hỏi về giá trị của mình. Ba android này hiện diện xuyên suốt game khi trải qua hành trình cảm xúc với những lựa chọn quyết định số phận của chúng và mục tiêu cuối cùng – có thể được định nghĩa theo nhiều cách khác nhau tùy thuộc vào giá trị của người chơi. Cốt truyện game đề cập đến nhiều chủ đề trưởng thành khám phá ranh giới đạo đức, và mỗi quyết định của người chơi ảnh hưởng đến kết cục.",
      "link": "https://www.www.quanticdream.com/en/detroit-become-human",
      "release": "25 tháng 5 năm 2018",
      "platforms": "PlayStation 4, PC",
      "genre": "Phiêu lưu",
      "developers": "Quantic Dream",
      "publishers": "Sony Interactive Entertainment / Quantic Dream",
      "inCart": false,
      "selected": false,
      "isHovered": false,
      "isLiked": false,
      "rating": 89,
      "id": "31",
      "cover": "https://res.cloudinary.com/gianlucajahn/image/upload/c_scale,q_100,w_500/v1658188602/detroit_a4kqkx.jpg",
      "footage": [
        "https://res.cloudinary.com/gianlucajahn/image/upload/v1658188602/detroit_a4kqkx.jpg",
        "https://res.cloudinary.com/gianlucajahn/image/upload/c_scale,q_100,w_1920/v1658238582/detroit_1_i8im17.jpg",
        "https://res.cloudinary.com/gianlucajahn/image/upload/c_scale,q_100,w_1920/v1658238582/detroit_2_yacxie.jpg",
        "https://res.cloudinary.com/gianlucajahn/image/upload/v1658238578/detroit_3_truscr.jpg"
      ]
    },
    {
      "name": "Tomb Raider",
      "surname": "tombraider",
      "price": "33.000 ₫",
      "desc": "Tomb Raider (thường gọi là Tomb Raider: A Survivor is Born) là phần thứ mười trong series Tomb Raider và phần đầu tiên trong lần reboot thứ hai của Crystal Dynamics. Một câu chuyện gốc đầy kịch tính và khắc nghiệt về Lara Croft, từ một cô gái trẻ sợ hãi trở thành người sống sót cứng cỏi. Chỉ vũ trang bằng bản năng nguyên thủy và khả năng vượt qua giới hạn chịu đựng của con người, Lara phải chiến đấu để khám phá lịch sử đen tối của một hòn đảo bị lãng quên và thoát khỏi sự kìm kẹp không ngừng của nó.",
      "link": "https://tombraider.square-enix-games.com/en-us",
      "release": "4 tháng 3 năm 2013",
      "platforms": "Linux, Xbox 360, Mac, PC, PlayStation 3",
      "genre": "Phiêu lưu",
      "developers": "Crystal Dynamics",
      "publishers": "Square Enix Europe",
      "inCart": false,
      "selected": false,
      "isHovered": false,
      "isLiked": false,
      "rating": 85,
      "id": "32",
      "cover": "https://res.cloudinary.com/gianlucajahn/image/upload/c_scale,q_100,w_500/v1658188613/tombraider_qx2xiy.jpg",
      "footage": [
        "https://res.cloudinary.com/gianlucajahn/image/upload/c_scale,q_100,w_1920/v1658188613/tombraider_qx2xiy.jpg",
        "https://res.cloudinary.com/gianlucajahn/image/upload/v1658238650/tombraider_1_jxeua4.jpg",
        "https://res.cloudinary.com/gianlucajahn/image/upload/v1658238650/tombraider_2_fnhmmd.jpg",
        "https://res.cloudinary.com/gianlucajahn/image/upload/v1658238650/tombraider_3_cr0yee.jpg"
      ]
    },
    {
      "name": "Elden Ring",
      "surname": "eldenring",
      "price": "643.500 ₫",
      "desc": "ELDEN RING là một tựa game hành động nhập vai thế giới mở được phát triển bởi FromSoftware và Bandai Namco Entertainment. Người chơi sẽ khám phá vùng đất Lands Between rộng lớn, chiến đấu với các kẻ thù hung dữ, thu thập rune để nâng cấp sức mạnh và đối đầu với các boss khổng lồ để trở thành Elden Lord. Thế giới được sáng tạo bởi Hidetaka Miyazaki và George R. R. Martin, mang đến trải nghiệm thử thách và đầy bất ngờ.",
      "link": "https://en.bandainamcoent.eu/elden-ring/elden-ring",
      "release": "25 tháng 2 năm 2022",
      "platforms": "PlayStation 4, PlayStation 5, Xbox One, Xbox Series X/S, PC",
      "genre": "Nhập vai",
      "developers": "FromSoftware",
      "publishers": "Bandai Namco Entertainment",
      "inCart": false,
      "selected": false,
      "isHovered": false,
      "isLiked": false,
      "rating": 96,
      "id": "33",
      "cover": "https://cdn.mos.cms.futurecdn.net/bByhky6jeMXqwxkPV9DZsg-1920-80.jpg",
      "footage": [
        "https://cdn.mos.cms.futurecdn.net/bByhky6jeMXqwxkPV9DZsg-1920-80.jpg",
        "https://assetsio.gnwcdn.com/elden-ring-cover-art.jpg?width=570&quality=85&format=jpg&dpr=3&auto=webp",
        "https://p325k7wa.twic.pics/high/elden-ring/elden-ring/08-shadow-of-the-erdtree/elden-ring-expansion-SOTE/00-page-content/ERSOTE-header-mobile.jpg?twic=v1/resize=760/step=10/quality=80",
        "https://cdn01.pinkoi.com/product/24rsWqPA/0/1/640x530.jpg"
      ]
    },
    {
      "name": "Baldur's Gate 3",
      "surname": "baldursgate3",
      "price": "742.500 ₫",
      "desc": "Baldur's Gate 3 là game nhập vai theo lượt dựa trên Dungeons & Dragons, phát triển bởi Larian Studios. Người chơi dẫn dắt một nhóm nhân vật bị nhiễm ký sinh trùng, khám phá thế giới Forgotten Realms, đưa ra lựa chọn ảnh hưởng đến cốt truyện và chiến đấu chiến lược. Với tự do cao, câu chuyện phong phú và đồ họa ấn tượng, đây là kiệt tác RPG hiện đại.",
      "link": "https://baldursgate3.game/",
      "release": "3 tháng 8 năm 2023",
      "platforms": "PC, PlayStation 5, Xbox Series X/S",
      "genre": "Nhập vai",
      "developers": "Larian Studios",
      "publishers": "Larian Studios",
      "inCart": false,
      "selected": false,
      "isHovered": false,
      "isLiked": false,
      "rating": 96,
      "id": "34",
      "cover": "https://www.dexerto.com/cdn-image/wp-content/uploads/2024/03/14/Baldurs-gate-3-body-img.jpg",
      "footage": [
        "https://www.dexerto.com/cdn-image/wp-content/uploads/2024/03/14/Baldurs-gate-3-body-img.jpg",
        "https://static0.gamerantimages.com/wordpress/wp-content/uploads/2024/01/bg3-lego-cover.jpg?w=1600&h=900&fit=crop",
        "https://miro.medium.com/0*lIgFfYSaabNN1oWm",
        "https://coverproject.sfo2.cdn.digitaloceanspaces.com/playstation_5/playstation_5.baldursgateiii_US.1694775307124177062_thumb.jpg"
      ]
    },
    {
      "name": "The Legend of Zelda: Tears of the Kingdom",
      "surname": "tearskingdom",
      "price": "1.690.000 ₫",
      "desc": "The Legend of Zelda: Tears of the Kingdom là phần tiếp theo của Breath of the Wild, nơi Link khám phá vương quốc Hyrule mở rộng với vùng trời và lòng đất. Sử dụng khả năng Ultrahand để xây dựng máy móc, Fuse để kết hợp vật phẩm và chiến đấu chống lại thế lực bóng tối để cứu công chúa Zelda. Game mang đến tự do sáng tạo vô tận trong thế giới mở.",
      "link": "https://www.nintendo.com/us/store/products/the-legend-of-zelda-tears-of-the-kingdom-switch/",
      "release": "12 tháng 5 năm 2023",
      "platforms": "Nintendo Switch",
      "genre": "Phiêu lưu",
      "developers": "Nintendo EPD",
      "publishers": "Nintendo",
      "inCart": false,
      "selected": false,
      "isHovered": false,
      "isLiked": false,
      "rating": 96,
      "id": "35",
      "cover": "https://www.gamereactor.eu/media/49/thisstunningnew_4164993b.jpg",
      "footage": [
        "https://www.gamereactor.eu/media/49/thisstunningnew_4164993b.jpg",
        "https://e.snmc.io/lk/nv/x/f4ceadebd7cb750ed0d015ed62b908c9/10962227",
        "https://pisces.bbystatic.com/image2/BestBuy_US/images/products/c5c6299b-b8c4-450a-901a-dbeeaa4b7d81.jpg;maxHeight=1920;maxWidth=900?format=webp",
        "https://www.rpgfan.com/wp-content/uploads/2022/09/The-Legend-of-Zelda-Tears-of-the-Kingdom-Cover-Art-US-296x480-320x240_c.jpg"
      ]
    },
    {
      "name": "Black Myth: Wukong",
      "surname": "blackmythwukong",
      "price": "1.299.000 ₫",
      "desc": "Black Myth: Wukong là game hành động nhập vai lấy cảm hứng từ thần thoại Trung Quốc và Tây Du Ký. Bạn hóa thân thành Định Mệnh Chi Nhân (Destined One), khám phá thế giới huyền bí, chiến đấu với yêu quái khổng lồ bằng gậy Như Ý, phép biến thân và các chiêu thức đa dạng. Với đồ họa Unreal Engine 5 tuyệt đẹp, boss chiến mãn nhãn và hành trình đầy thử thách, đây là một trong những tựa game xuất sắc nhất năm 2024.",
      "link": "https://www.heishenhua.com/",
      "release": "20 tháng 8 năm 2024",
      "platforms": "PlayStation 5, PC, Xbox Series X/S",
      "genre": "Nhập vai",
      "developers": "Game Science",
      "publishers": "Game Science",
      "inCart": false,
      "selected": false,
      "isHovered": false,
      "isLiked": false,
      "rating": 82,
      "id": "36",
      "cover": "https://cdn1.epicgames.com/spt-assets/ca9ef1bcf2f54043baac351366aec677/black-myth-wukong-jz9yr.jpg",
      "footage": [
        "https://cdn1.epicgames.com/spt-assets/ca9ef1bcf2f54043baac351366aec677/black-myth-wukong-jz9yr.jpg",
        "https://www.dsogaming.com/wp-content/uploads/2024/06/Black-Myth-Wukong-screenshot_02.jpg",
        "https://www.gematsu.com/wp-content/uploads/2022/08/Black-Myth_08-19-22.jpg",
        "https://preview.redd.it/new-black-myth-wukong-screenshot-breathtaking-v0-mmrc6y4gh4jd1.jpeg?auto=webp&s=5ab4e31e8fba2582db5ffaf10b6c438a51662b2b"
      ]
    },
    {
      "name": "Marvel's Spider-Man 2",
      "surname": "spiderman2",
      "price": "1.999.000 ₫",
      "desc": "Marvel's Spider-Man 2 cho phép điều khiển Peter Parker và Miles Morales trong New York rộng lớn, chiến đấu với các villain như Venom và Kraven. Với hệ thống chiến đấu mượt mà, web-swinging đỉnh cao và cốt truyện cảm xúc về tình bạn, trách nhiệm.",
      "link": "https://www.playstation.com/en-us/games/marvels-spider-man-2/",
      "release": "20 tháng 10 năm 2023",
      "platforms": "PlayStation 5, PC (30/01/2026)",
      "genre": "Phiêu lưu",
      "developers": "Insomniac Games",
      "publishers": "Sony Interactive Entertainment",
      "inCart": false,
      "selected": false,
      "isHovered": false,
      "isLiked": false,
      "rating": 90,
      "id": "37",
      "cover": "https://4kwallpapers.com/images/wallpapers/marvels-spider-man-3840x2160-11609.jpeg",
      "footage": [
        "https://4kwallpapers.com/images/wallpapers/marvels-spider-man-3840x2160-11609.jpeg",
        "https://gamingbolt.com/wp-content/uploads/2024/10/marvels-spider-man-2-pc-image-2.jpg",
        "https://www.playstationlifestyle.net/wp-content/uploads/sites/9/2023/06/spider-2-concept.jpg",
        "https://i.redd.it/8wwi30k20u961.jpg"
      ]
    },
    {
      "name": "Resident Evil 4 Remake",
      "surname": "residentevil4remake",
      "price": "340.000 ₫",
      "desc": "Resident Evil 4 Remake đưa Leon S. Kennedy đến Tây Ban Nha để cứu con gái tổng thống khỏi giáo phái Los Illuminados. Với đồ họa hiện đại, chiến đấu over-the-shoulder căng thẳng và yếu tố kinh dị sinh tồn, đây là phiên bản làm lại hoàn hảo của kiệt tác kinh điển.",
      "link": "https://www.residentevil.com/re4/",
      "release": "24 tháng 3 năm 2023",
      "platforms": "PlayStation 4, PlayStation 5, Xbox Series X/S, PC",
      "genre": "Kinh dị sinh tồn",
      "developers": "Capcom",
      "publishers": "Capcom",
      "inCart": false,
      "selected": false,
      "isHovered": false,
      "isLiked": false,
      "rating": 96,
      "id": "38",
      "cover": "https://cdna.artstation.com/p/assets/images/images/060/947/604/large/yin-shiuan-resident-evil-4-remake.jpg?1679663576",
      "footage": [
        "https://cdna.artstation.com/p/assets/images/images/060/947/604/large/yin-shiuan-resident-evil-4-remake.jpg?1679663576",
        "https://preview.redd.it/idmjlql391g51.png?auto=webp&s=aef86caaaadc1f4a9a813ca94ab85716a33dd5bb",
        "https://i.redd.it/sdcev2ze46qa1.png",
        "https://image.api.playstation.com/vulcan/ap/rnd/202402/0907/307bf27242bb288e27f8bf745037a1d035081db1f22d2c71.png?w=440"
      ]
    },
    {
      "name": "Hogwarts Legacy",
      "surname": "hogwartslegacy",
      "price": "129.000 ₫",
      "desc": "Hogwarts Legacy đưa người chơi vào thế giới phù thủy Harry Potter thế kỷ 19, nhập vai học sinh Hogwarts, học phép thuật, khám phá lâu đài và thế giới mở, chiến đấu với goblin và khám phá bí mật cổ xưa. Trải nghiệm tự do khám phá và tùy chỉnh nhân vật.",
      "link": "https://www.hogwartslegacy.com/",
      "release": "10 tháng 2 năm 2023",
      "platforms": "PlayStation 4, PlayStation 5, Xbox One, Xbox Series X/S, PC, Nintendo Switch",
      "genre": "Nhập vai",
      "developers": "Avalanche Software",
      "publishers": "Warner Bros. Games",
      "inCart": false,
      "selected": false,
      "isHovered": false,
      "isLiked": false,
      "rating": 84,
      "id": "39",
      "cover": "https://static0.gamerantimages.com/wordpress/wp-content/uploads/2021/08/hogwarts-legacy-giant-spider.jpg?w=1200&h=675&fit=crop",
      "footage": [
        "https://static0.gamerantimages.com/wordpress/wp-content/uploads/2021/08/hogwarts-legacy-giant-spider.jpg?w=1200&h=675&fit=crop",
        "https://hb.imgix.net/f414c5d002517cfe7af54a54ce88d66523d4f158.png?auto=compress,format&fit=crop&h=353&w=616&s=0e5be3f9fc3452eebb56135ee6b005f7",
        "https://www.syfy.com/sites/syfy/files/2023/01/the_art_and_making_of_hogwarts_legacy.jpg",
        "https://ar-pay.com/blog/wp-content/uploads/2024/08/Unveiling-Hogwarts-Legacy-Gameplay.jpg"
      ]
    },
    {
      "name": "Forza Horizon 5",
      "surname": "forzahorizon5",
      "price": "495.000 ₫",
      "desc": "Forza Horizon 5 diễn ra tại Mexico rộng lớn với địa hình đa dạng từ sa mạc đến rừng rậm. Người chơi tham gia festival đua xe Horizon, thu thập hơn 500 xe, tùy chỉnh và thi đấu trong thế giới mở sống động với thời tiết động.",
      "link": "https://www.forzamotorsport.net/en-us/games/fh5",
      "release": "9 tháng 11 năm 2021",
      "platforms": "Xbox One, Xbox Series X/S, PC",
      "genre": "Đua xe",
      "developers": "Playground Games",
      "publishers": "Xbox Game Studios",
      "inCart": false,
      "selected": false,
      "isHovered": false,
      "isLiked": false,
      "rating": 92,
      "id": "40",
      "cover": "https://cdn.theouterhaven.net/wp-content/uploads/2021/08/Forza-Horizon-5-Cover-Art-Header-Image_01-e1634661962864.jpg",
      "footage": [
        "https://cdn.theouterhaven.net/wp-content/uploads/2021/08/Forza-Horizon-5-Cover-Art-Header-Image_01-e1634661962864.jpg",
        "https://i.ytimg.com/vi/eh2sGze-8G0/maxresdefault.jpg",
        "https://images.greenmangaming.com/2c3b8ab05a12409c8ec93487c4f3935a/fec44402e0f1413ca52d2fe123471df0.jpg",
        "https://preview.redd.it/high-quality-cover-print-for-forza-horizon-5-for-pc-put-v0-42pno6vphsqd1.jpeg?width=1080&crop=smart&auto=webp&s=ca874f9f8a9da335f93b29e6a66df112e42300f2"
      ]
    },
    {
      "name": "Star Wars Jedi: Survivor",
      "surname": "jedisurvivor",
      "price": "163.500 ₫",
      "desc": "Star Wars Jedi: Survivor tiếp nối hành trình của Cal Kestis 5 năm sau Fallen Order, trốn chạy Đế chế, khám phá các hành tinh mới, nâng cấp lightsaber và Force powers để chiến đấu với kẻ thù. Kết hợp platforming, combat và câu chuyện Star Wars hấp dẫn.",
      "link": "https://www.ea.com/games/starwars/jedi-survivor",
      "release": "28 tháng 4 năm 2023",
      "platforms": "PlayStation 5, Xbox Series X/S, PC",
      "genre": "Phiêu lưu",
      "developers": "Respawn Entertainment",
      "publishers": "Electronic Arts",
      "inCart": false,
      "selected": false,
      "isHovered": false,
      "isLiked": false,
      "rating": 85,
      "id": "41",
      "cover": "https://cdna.artstation.com/p/assets/images/images/069/938/982/large/volta-ea-applejack-keyart01-full-illustration-4k.jpg?1701356056",
      "footage": [
        "https://cdna.artstation.com/p/assets/images/images/069/938/982/large/volta-ea-applejack-keyart01-full-illustration-4k.jpg?1701356056",
        "https://pbs.twimg.com/media/GvXnNGIXIAA_dxV.jpg",
        "https://games-b26f.kxcdn.com/wp-content/uploads/2024/01/jedi-survivor-8-ezgif.com-webp-to-jpg-converter-770x470.jpg",
        "https://atthemoviesshop.com/cdn/shop/files/star-wars-jedi-survivor-vinyl-soundtrack-atm-packshot_460x@2x.webp?v=1725881570"
      ]
    },
    {
      "name": "Assassin's Creed Mirage",
      "surname": "assassinscreedmirage",
      "price": "237.000 ₫",
      "desc": "Assassin's Creed Mirage đưa Basim Ibn Ishaq trở thành Assassin ở Baghdad thế kỷ 9, tập trung vào stealth, parkour và ám sát. Khám phá thành phố sống động, học kỹ năng từ Hidden Ones và khám phá bí mật về quá khứ của mình.",
      "link": "https://www.ubisoft.com/en-us/game/assassins-creed/mirage",
      "release": "5 tháng 10 năm 2023",
      "platforms": "PlayStation 4, PlayStation 5, Xbox One, Xbox Series X/S, PC",
      "genre": "Hành động",
      "developers": "Ubisoft Bordeaux",
      "publishers": "Ubisoft",
      "inCart": false,
      "selected": false,
      "isHovered": false,
      "isLiked": false,
      "rating": 76,
      "id": "42",
      "cover": "https://mir-s3-cdn-cf.behance.net/project_modules/1400/09e726154938805.64947f37d43cb.jpg",
      "footage": [
        "https://mir-s3-cdn-cf.behance.net/project_modules/1400/09e726154938805.64947f37d43cb.jpg",
        "https://preview.redd.it/gameinformer-cover-reveal-assassins-creed-mirage-v0-ceemxdhxp2lb1.jpg?auto=webp&s=8cae4e2063f4e407eaad076897d342d40412ace7",
        "https://i.redd.it/xwky1pqw2ctf1.jpeg",
        "https://media.altchar.com/prod/images/gm_article_embed_image/05e2fae8172d-ac-mirage-ps5-cover.jpg"
      ]
    },
    {
      "name": "Unpacking",
      "surname": "unpacking",
      "price": "99.000 ₫",
      "desc": "Một trò chơi giải đố nhẹ nhàng, nơi bạn mở các thùng đồ và sắp xếp chúng vào ngôi nhà mới. Qua từng món đồ, bạn sẽ dần khám phá ra câu chuyện cuộc đời của nhân vật mà không cần một lời thoại nào.",
      "link": "https://store.steampowered.com/app/1135690/Unpacking/",
      "release": "1 tháng 11 năm 2021",
      "platforms": "Nintendo Switch, PlayStation 4/5, Xbox One, PC",
      "genre": "Giải đố",
      "developers": "Witch Beam",
      "publishers": "Humble Games",
      "inCart": false,
      "selected": false,
      "isHovered": false,
      "isLiked": false,
      "rating": 93,
      "id": "1135690",
      "cover": "https://witchbeam.com.au/wp-content/uploads/2020/09/unpacking_maincapsule-e1635550190906.png",
      "footage": [
        "https://unpackinggame.com/wp-content/uploads/2021/09/Screenshot02.png",
        "https://unpackinggame.com/wp-content/uploads/2021/09/Screenshot01.png",
        "https://static0.thegamerimages.com/wordpress/wp-content/uploads/2022/09/Unpacking-Beginner-Tips-Feature-Image.jpg",
        "https://static0.srcdn.com/wordpress/wp-content/uploads/2022/01/Unpacking-Final-Shot.jpg"
      ]
    },
    {
      "name": "DAVE THE DIVER",
      "surname": "davethediver",
      "price": "143.000 ₫",
      "desc": "Một trò chơi phiêu lưu dưới đại dương xanh mướt vào ban ngày và quản lý nhà hàng sushi vào ban đêm. Đồ họa pixel cực kỳ đáng yêu cùng lối chơi gây nghiện sẽ khiến bạn không thể rời mắt.",
      "link": "https://store.steampowered.com/app/1868140/DAVE_THE_DIVER/",
      "release": "28 tháng 6 năm 2023",
      "platforms": "Nintendo Switch, PlayStation 5, PC",
      "genre": "Phiêu lưu",
      "developers": "MINTROCKET",
      "publishers": "MINTROCKET",
      "inCart": false,
      "selected": false,
      "isHovered": false,
      "isLiked": false,
      "rating": 96,
      "id": "1868140",
      "cover": "https://gaming-cdn.com/images/products/14242/orig/dave-the-diver-pc-mac-game-steam-europe-and-us-and-canada-cover.jpg?v=1744274918",
      "footage": [
        "https://gamelade1.sgp1.cdn.digitaloceanspaces.com/wp-content/uploads/2025/12/b-3.jpg",
        "https://herogame.vn/upload/images/img_30_04_2024/game-dave-the-diver-anniversary-edition-nintendo-switch-4_894291_663003d205e6d6.20826904.jpg",
        "https://static0.thegamerimages.com/wordpress/wp-content/uploads/2023/07/dave-the-diver-x-best-bosses.jpg?w=1600&h=1200&fit=crop",
        "https://completexbox.co.uk/wp-content/uploads/2025/12/DAVE-THE-DIVER-header.webp"
      ]
    },
    {
      "name": "Persona 5 Royal",
      "surname": "p5r",
      "price": "414.000 ₫",
      "desc": "Đeo mặt nạ và tham gia băng Phantom Thieves of Hearts khi họ thực hiện những vụ trộm chấn động. Bản Royal bao gồm thêm nội dung cốt truyện và nhân vật mới.",
      "link": "https://store.steampowered.com/app/1687950/Persona_5_Royal/",
      "release": "21 tháng 10 năm 2022",
      "platforms": "PlayStation 5, Xbox Series X/S, Nintendo Switch, PC",
      "genre": "Nhập vai Nhật Bản",
      "developers": "ATLUS",
      "publishers": "SEGA",
      "inCart": false,
      "selected": false,
      "isHovered": false,
      "isLiked": false,
      "rating": 97,
      "id": "1687950",
      "cover": "https://store-images.s-microsoft.com/image/apps.6136.14482474285447263.0a4055ed-9044-4c0c-abf5-292bb1bcb735.3db4c9c4-de15-4e0f-8b4d-1539f8a2ab08?q=90&w=480&h=270",
      "footage": [
        "https://images.bauerhosting.com/legacy/media/5e7a/4866/47b3/f17c/af0a/380b/persona-5-royal-1.jpg?ar=16%3A9&fit=crop&crop=top&auto=format&w=1440&q=80",
        "https://i.redd.it/dednarspqar41.jpg",
        "https://preview.redd.it/persona-5-will-be-my-first-rpg-any-combat-advice-v0-ftmg64w0qhfb1.jpg?width=1080&crop=smart&auto=webp&s=e1481a451aafa123bab8cb2d734928f760c5253b",
        "https://images.rpgsite.net/image/da49c9a1/84556/original/persona_5_confidant_guide.png"
      ]
    },
    {
      "name": "Persona 3 Reload",
      "surname": "p3r",
      "price": "409.000 ₫",
      "desc": "Bước vào Dark Hour và đánh thức chiều sâu của trái tim bạn. Một bản tái hiện hoàn toàn mới của tựa game RPG định nghĩa thể loại.",
      "link": "https://store.steampowered.com/app/2161700/Persona_3_Reload/",
      "release": "2 tháng 2 năm 2024",
      "platforms": "PlayStation 4/5, Xbox One, Xbox Series X/S, PC",
      "genre": "Nhập vai Nhật Bản",
      "developers": "ATLUS",
      "publishers": "SEGA",
      "inCart": false,
      "selected": false,
      "isHovered": false,
      "isLiked": false,
      "rating": 95,
      "id": "2161700",
      "cover": "https://shared.fastly.steamstatic.com/store_item_assets/steam/apps/2161700/header.jpg?t=1762545767",
      "footage": [
        "https://static0.thegamerimages.com/wordpress/wp-content/uploads/wm/2024/09/the-members-of-sees-with-mitsuru-s-dad-in-persona-3-reload.jpg?w=1600&h=900&fit=crop",
        "https://asia.sega.com/p3r/en/switch2/resources/img/top/overview-pict-1_7fbb88e4541a5d7ac9aa.webp",
        "https://cdn.mos.cms.futurecdn.net/6d4rT7Sum4JrJMmMyzRNp7.jpg",
        "https://mlpnk72yciwc.i.optimole.com/cqhiHLc.IIZS~2ef73/w:auto/h:auto/q:75/https://bleedingcool.com/wp-content/uploads/2024/03/Persona-3-Reload-Expansion-Pass-Art.jpg"
      ]
    },
    {
      "name": "Persona 4 Golden",
      "surname": "p4g",
      "price": "190.000 ₫",
      "desc": "Một câu chuyện về sự trưởng thành đưa nhân vật chính và những người bạn vào một cuộc hành trình sau một chuỗi những vụ giết người hàng loạt. Hãy khám phá thế giới bên trong tivi, đối mặt với bản ngã đen tối của chính mình để tìm ra sự thật cuối cùng đằng sau màn sương mù.",
      "link": "https://store.steampowered.com/app/1113000/Persona_4_Golden/",
      "release": "13 tháng 6 năm 2020",
      "platforms": "PlayStation Vita, PlayStation 4, Xbox One, Nintendo Switch, PC",
      "genre": "Nhập vai Nhật Bản",
      "developers": "ATLUS",
      "publishers": "SEGA",
      "inCart": false,
      "selected": false,
      "isHovered": false,
      "isLiked": false,
      "rating": 97,
      "id": "1113000",
      "cover": "https://www.nintendo.com/eu/media/images/10_share_images/games_15/nintendo_switch_download_software_1/2x1_NSwitchDS_Persona4Golden.jpg",
      "footage": [
        "https://sm.pcmag.com/pcmag_au/review/p/persona-4-/persona-4-golden-for-pc_xpe3.jpg",
        "https://preview.redd.it/should-i-buy-persona-4-golden-v0-siko3j8m8f9d1.jpeg?width=640&crop=smart&auto=webp&s=e1481a451aafa123bab8cb2d734928f760c5253b",
        "https://www.megavisions.net/wp-content/uploads/2020/08/persona_4_goldenopcsteamsales.jpg",
        "https://assets2.ignimgs.com/2012/11/21/p4g1119121600jpg-f2b620.jpg"
      ]
    },
    {
      "name": "Hades II",
      "surname": "hades2",
      "price": "288.500 ₫",
      "desc": "Phần tiếp theo của tựa game rogue-like hành động đoạt giải Game of the Year. Lần này bạn sẽ vào vai Melinoë, công chúa của Địa ngục, sử dụng ma thuật hắc ám để đối đầu với Titan của Thời gian.",
      "link": "https://store.steampowered.com/app/1145350/Hades_II/",
      "release": "6 tháng 5 năm 2024 (Early Access)",
      "platforms": "PC",
      "genre": "Hành động",
      "developers": "Supergiant Games",
      "publishers": "Supergiant Games",
      "inCart": false,
      "selected": false,
      "isHovered": false,
      "isLiked": false,
      "rating": 98,
      "id": "1145350",
      "cover": "https://pcmarket.vn/media/news/471-thumb.jpg",
      "footage": [
        "https://cdn.cdkeys.com/media/catalog/product/h/a/hades2-steam4.jpg",
        "https://cdn.hstatic.net/files/1000154920/file/game_nintendo_switch_2_-_hades_ii_1024x1024.jpg",
        "https://static.wixstatic.com/media/a511ef_1bd9b81c0d54418aba578f147d331ef6~mv2.jpeg/v1/fill/w_568,h_320,al_c,q_80,usm_0.66_1.00_0.01,enc_avif,quality_auto/a511ef_1bd9b81c0d54418aba578f147d331ef6~mv2.jpeg",
        "https://shared.fastly.steamstatic.com/store_item_assets/steam/bundles/61368/1oamp11nx26flnh4/99b84caa02ff4453758fc6dd94fd137315490a91/header.jpg?t=1761679817"
      ]
    },
    {
      "name": "Ori and the Will of the Wisps",
      "surname": "oriwotw",
      "price": "172.000 ₫",
      "desc": "Một trong những tựa game đẹp nhất mọi thời đại. Hãy cùng chú tinh linh Ori dấn thân vào một hành trình mới trong thế giới rộng lớn, giải cứu người bạn phương xa.",
      "link": "https://store.steampowered.com/app/1057090/Ori_and_the_Will_of_the_Wisps/",
      "release": "11 tháng 3 năm 2020",
      "platforms": "Nintendo Switch, Xbox One, PC",
      "genre": "Phiêu lưu",
      "developers": "Moon Studios",
      "publishers": "Xbox Game Studios",
      "inCart": false,
      "selected": false,
      "isHovered": false,
      "isLiked": false,
      "rating": 96,
      "id": "1057090",
      "cover": "https://assets.nintendo.com/image/upload/ar_16:9,c_lpad,w_1240/b_white/f_auto/q_auto/store/software/switch/70010000034725/cf74916275780188fd850512efe6c678318d7317bf987599205d2a3fc76dbd79",
      "footage": [
        "https://divineshop.vn/image/ckeditor/ss_0cf0ec6681ae5771173790dbc99ddb3bf3b886ad.jpg",
        "https://platform.theverge.com/wp-content/uploads/sites/2/chorus/uploads/chorus_asset/file/19784917/prologueInGame.png?quality=90&strip=all&crop=0,3.4613147178592,100,93.077370564282",
        "https://i0.wp.com/thegamingoutsider.com/wp-content/uploads/2020/03/Will-of-the-Wisps-3.jpg?ssl=1",
        "https://i.ytimg.com/vi/XQiRQzNi4AQ/maxresdefault.jpg"
      ]
    },
    {
      "name": "Viewfinder",
      "surname": "viewfinder",
      "price": "112.500 ₫",
      "desc": "Thách thức mọi giác quan và định hình lại thế giới xung quanh bằng một chiếc máy ảnh lấy liền. Chụp ảnh và đưa chúng vào đời thực để vượt qua các chướng ngại vật.",
      "link": "https://store.steampowered.com/app/1382890/Viewfinder/",
      "release": "18 tháng 7 năm 2023",
      "platforms": "PlayStation 5, PC",
      "genre": "Giải đố",
      "developers": "Sad Owl Studios",
      "publishers": "Thunderful Publishing",
      "inCart": false,
      "selected": false,
      "isHovered": false,
      "isLiked": false,
      "rating": 92,
      "id": "1382890",
      "cover": "https://shared.fastly.steamstatic.com/store_item_assets/steam/apps/1382070/a69eb56f73446624325dec8a4fe74dc4ae09fb96/header.jpg?t=1764842475",
      "footage": [
        "https://static0.srcdn.com/wordpress/wp-content/uploads/2023/07/camera-taking-photo-in-viewfinder.jpg?q=50&fit=crop&w=825&dpr=1.5",
        "https://d1lss44hh2trtw.cloudfront.net/resize?type=webp&url=https%3A%2F%2Fshacknews-www.s3.amazonaws.com%2Fassets%2Feditorial%2F2023%2F07%2Fviewfinder-review-1.jpg&width=986&sign=PTwAMjJotAi0F3QS4uQI4QeTee9xtJjVOH5easydKNc",
        "https://static.actugaming.net/media/2023/07/viewfinder-test-screenshots-13.jpg",
        "https://encrypted-tbn0.gstatic.com/images?q=tbn:ANd9GcQODELvGyxPlBojQ6JJ1U1kFO28l9bVlmedjA&s"
      ]
    },
    {
      "name": "Dorfromantik",
      "surname": "dorfromantik",
      "price": "96.000 ₫",
      "desc": "Một trò chơi chiến thuật xây dựng và giải đố thư giãn, nơi bạn tạo ra một cảnh quan làng quê ngày càng mở rộng bằng cách đặt các ô gạch hình lục giác.",
      "link": "https://store.steampowered.com/app/1455840/Dorfromantik/",
      "release": "28 tháng 4 năm 2022",
      "platforms": "Nintendo Switch, PC",
      "genre": "Thông thường",
      "developers": "Toukana Interactive",
      "publishers": "Toukana Interactive",
      "inCart": false,
      "selected": false,
      "isHovered": false,
      "isLiked": false,
      "rating": 97,
      "id": "1455840",
      "cover": "https://gamelade.vn/wp-content/uploads/2025/05/maxresdefault-11.jpg",
      "footage": [
        "https://cdn.dlcompare.com/game_tetiere/upload/gameimage/file/76835.jpg.webp",
        "https://superraregames.com/cdn/shop/files/Dorfromantik-gameplay-2@2x.jpg?v=1710262555",
        "https://deathisawhale.com/wp-content/uploads/2022/09/20220722210157_1.jpg?w=930&h=450&crop=1",
        "https://i.redd.it/dorfromantik-is-a-wonderful-game-with-a-very-high-replay-v0-o2eh0fyuptmb1.jpg?width=1280&format=pjpg&auto=webp&s=a213b4ed3bac53a5fe02cbff3af4cfea78a7041c"
      ]
    },
    {
      "name": "Stray",
      "surname": "stray",
      "price": "227.500 ₫",
      "desc": "Lạc lối, cô độc và xa cách gia đình, một chú mèo hoang phải giải mã một bí ẩn cổ xưa để thoát khỏi một thành phố mạng (cybercity) đang dần tàn lụi và tìm đường về nhà.",
      "link": "https://store.steampowered.com/app/1332010/Stray/",
      "release": "19 tháng 7 năm 2022",
      "platforms": "PlayStation 4/5, Xbox One, Xbox Series X/S, PC",
      "genre": "Phiêu lưu",
      "developers": "BlueTwelve Studio",
      "publishers": "Annapurna Interactive",
      "inCart": false,
      "selected": false,
      "isHovered": false,
      "isLiked": false,
      "rating": 97,
      "id": "1332010",
      "cover": "https://shared.akamai.steamstatic.com/store_item_assets/steam/apps/1332010/capsule_616x353.jpg?t=1733260906",
      "footage": [
        "https://pyxis.nymag.com/v1/imgs/dda/385/b3aa8500e7d2135714ddf15a629280b3f2-Stray3.rhorizontal.w700.png",
        "https://adventuregamehotspot.com/images/posts/262/382-stray-review-teaser.jpg",
        "https://shared.akamai.steamstatic.com/store_item_assets/steam/apps/1332010/ss_e8f0cbd5efdba352e89c4cfcee3fe991a1e1be8a.1920x1080.jpg?t=1733260906",
        "https://cdn.mos.cms.futurecdn.net/StLJWJPix4aaeecBGKMHxc-1200-80.jpg"
      ]
    },
    {
      "name": "Animal Well",
      "surname": "animalwell",
      "price": "218.500 ₫",
      "desc": "Khám phá một mê cung siêu thực, kết nối sâu sắc với những sinh vật kỳ lạ. Một trò chơi giải đố Metroidvania có đồ họa pixel cực kỳ tinh xảo và chứa đựng hàng ngàn bí mật ẩn giấu.",
      "link": "https://store.steampowered.com/app/813230/ANIMAL_WELL/",
      "release": "9 tháng 5 năm 2024",
      "platforms": "Nintendo Switch, PlayStation 5, PC",
      "genre": "Giải đố",
      "developers": "Shared Memory",
      "publishers": "Bigmode",
      "inCart": false,
      "selected": false,
      "isHovered": false,
      "isLiked": false,
      "rating": 91,
      "id": "813230",
      "cover": "https://shared.akamai.steamstatic.com/store_item_assets/steam/apps/813230/capsule_616x353.jpg?t=1736282851",
      "footage": [
        "https://encrypted-tbn0.gstatic.com/images?q=tbn:ANd9GcTWoJF2T-LUr8gXjt5D0h25pnYG_ehvt8hJUw&s",
        "https://alexlovendahl.com/wp-content/uploads/2025/01/animal-well-1.jpg",
        "https://www.animalwell.net/youtubeBanner.jpg",
        "https://d1lss44hh2trtw.cloudfront.net/resize?type=webp&url=https%3A%2F%2Fshacknews-www.s3.amazonaws.com%2Fassets%2Farticle%2F2024%2F03%2F21%2Fanimal-well-featured_feature.jpg&width=1032&sign=Yi3Kr_tfVYUEMCFpitPA6LGiSoYMWCwPUTPCu5GPmKE"
      ]
    },
    {
      "name": "Townscaper",
      "surname": "townscaper",
      "price": "35.000 ₫",
      "desc": "Không có mục tiêu, không có áp lực. Đơn giản là xây dựng những thị trấn nhỏ xinh xắn trên mặt nước bằng cách nhấp chuột. Một trải nghiệm nghệ thuật và giải trí cực kỳ thư giãn.",
      "link": "https://store.steampowered.com/app/1291340/Townscaper/",
      "release": "26 tháng 8 năm 2021",
      "platforms": "Nintendo Switch, PC, Mobile",
      "genre": "Thông thường",
      "developers": "Oskar Stålberg",
      "publishers": "Raw Fury",
      "inCart": false,
      "selected": false,
      "isHovered": false,
      "isLiked": false,
      "rating": 97,
      "id": "1291340",
      "cover": "https://cdn1.epicgames.com/salesEvent/salesEvent/EGS_Townscaper_OskarStlberg_S3_2560x1440-558540cb0b62cb5520f1f9e5b4c7a204",
      "footage": [
        "https://play-lh.googleusercontent.com/H5uuTwgyskAzYYlEPD9ak0v0Yjigs9fmzI8ApiEqMt5i5xgo7EXs_0qdosZ3cE4rKtU=w526-h296-rw",
        "https://hoanghamobile.com/tin-tuc/wp-content/uploads/2024/08/Townscaper.jpg",
        "https://cdn2.fptshop.com.vn/unsafe/Uploads/images/tin-tuc/166300/Originals/Townscaper-1.jpg",
        "https://encrypted-tbn0.gstatic.com/images?q=tbn:ANd9GcSlp5SM8DuFQ-u9Fbgd2oCsfY-hcrd4gmmphQ&s"
      ]
    },
    {
      "name": "Tiny Glade",
      "surname": "tinyglade",
      "price": "153.500 ₫",
      "desc": "Một trò chơi xây dựng tự do không có lưới, cho phép bạn tạo ra các lâu đài cổ tích, những tàn tích rêu phong và các khu vườn thơ mộng với cảm giác cực kỳ êm dịu.",
      "link": "https://store.steampowered.com/app/2198150/Tiny_Glade/",
      "release": "23 tháng 9 năm 2024",
      "platforms": "PC",
      "genre": "Thông thường",
      "developers": "Pounce Light",
      "publishers": "Pounce Light",
      "inCart": false,
      "selected": false,
      "isHovered": false,
      "isLiked": false,
      "rating": 96,
      "id": "2198150",
      "cover": "https://cdn2.fptshop.com.vn/unsafe/1920x0/filters:format(webp):quality(75)/tiny_glade_thum_47a0e46bf1.jpg",
      "footage": [
        "https://cdn.mos.cms.futurecdn.net/i2CKeQ4XPbkJLZLGpVGion.jpg",
        "https://eqobpdqkx9u.exactdn.com/wp-content/uploads/2024/09/tinyglade-3.jpg?strip=all&sharp=1",
        "https://gaming.buzz/wp-content/uploads/2024/08/Tiny-Glade-22_08_2024-16_37_30-min-1024x576.jpg",
        "https://www.destructoid.com/wp-content/uploads/2024/10/tiny-glade-builds.jpg"
      ]
    },
    {
      "name": "Balatro",
      "surname": "balatro",
      "price": "174.000 ₫",
      "desc": "Một trò chơi xây dựng bộ bài (deck-builder) lấy cảm hứng từ Poker. Hãy tìm ra những sự kết hợp mạnh mẽ (jokers) để tạo ra những chuỗi điểm kỷ lục trong tựa game gây nghiện nhất năm 2024.",
      "link": "https://store.steampowered.com/app/2379780/Balatro/",
      "release": "20 tháng 2 năm 2024",
      "platforms": "Nintendo Switch, PS5, Xbox Series X/S, PC",
      "genre": "Chiến lược",
      "developers": "LocalThunk",
      "publishers": "Playstack",
      "inCart": false,
      "selected": false,
      "isHovered": false,
      "isLiked": false,
      "rating": 97,
      "id": "2379780",
      "cover": "https://upload.wikimedia.org/wikipedia/en/8/89/Balatro_cover.jpg",
      "footage": [
        "https://shared.akamai.steamstatic.com/store_item_assets/steam/apps/2379780/96208723dbedef49d71bf1b0a74aee1689018c50/ss_96208723dbedef49d71bf1b0a74aee1689018c50.1920x1080.jpg?t=1762516142",
        "https://i.guim.co.uk/img/media/08567005721d112a0f138bfce795285cf4d7aea1/0_0_1920_1080/master/1920.jpg?width=700&quality=85&auto=format&fit=max&s=515ed152605ccf37a54c23fdd21a023b",
        "https://kamikey.com/wp-content/uploads/2025/07/balatro.jpg",
        "https://minhtuanmobile.com/uploads/blog/cach-tai-va-choi-balatro-vua-gay-sot-the-game-awards-2024-241213020149.jpg"
      ]
    }
  ]
}